Workbook
Name Slicer_Denial_or_Exception: #N/A
Name Slicer_Payment_Status: #N/A
Name Slicer_Region: #N/A
Name Slicer_Service_Category: #N/A

Sheet revenue_billing_raw_data_sample
A1: Invoice_ID | B1: Customer_Name | C1: Invoice_Date | D1: Due_Date | E1: Payment_Date | F1: Region | G1: Service_Category | H1: Billed_Amount | I1: Paid_Amount | J1: Payment_Status | K1: Denial_or_Exception | L1: Exception_Reason | M1: Account_Manager
A2: INV-1017 | B2: Hillcrest Diagnostics | C2: 45717 | D2: 45747 | F2: Central | G2: Billing Support | H2: 342.85 | I2: 0 | J2: Unpaid | K2: No | L2: None | M2: K. Brown
A3: INV-1022 | B3: Summit Health | C3: 45720 | D3: 45750 | E3: 45732 | F3: North | G3: Revenue Audit | H3: 1012.03 | I3: 1012.03 | J3: Paid | K3: Yes | L3: Eligibility issue | M3: R. Nguyen
A4: INV-1238 | B4: Summit Health | C4: 45720 | D4: 45750 | E4: 45765 | F4: East | G4: Claims Review | H4: 2286.94 | I4: 2286.94 | J4: Paid | K4: No | L4: None | M4: A. Lopez
A5: INV-1037 | B5: Hillcrest Diagnostics | C5: 45721 | D5: 45751 | F5: Central | G5: Billing Support | H5: 527.89 | I5: 0 | J5: Unpaid | K5: Yes | L5: Denied claim | M5: R. Nguyen
A6: INV-1234 | B6: Blue Ridge Medical | C6: 45721 | D6: 45751 | F6: East | G6: RCM Consulting | H6: 2036.95 | I6: 0 | J6: Unpaid | K6: Yes | L6: Coding issue | M6: S. Patel
A7: INV-1239 | B7: Red Oak Wellness | C7: 45722 | D7: 45752 | E7: 45749 | F7: East | G7: Revenue Audit | H7: 4371.67 | I7: 4371.67 | J7: Paid | K7: No | L7: None | M7: M. Diaz
A8: INV-1179 | B8: Westgate Family Health | C8: 45727 | D8: 45757 | F8: West | G8: Claims Review | H8: 3042.68 | I8: 0 | J8: Unpaid | K8: Yes | L8: Denied claim | M8: J. Smith
A9: INV-1210 | B9: Parkview Internal Medicine | C9: 45728 | D9: 45758 | E9: 45739 | F9: North | G9: Claims Review | H9: 2328.92 | I9: 2328.92 | J9: Paid | K9: No | L9: None | M9: S. Patel
A10: INV-1246 | B10: Valley Care Center | C10: 45728 | D10: 45758 | E10: 45780 | F10: West | G10: Billing Support | H10: 1940.77 | I10: 1940.77 | J10: Paid | K10: Yes | L10: Eligibility issue | M10: J. Smith
A11: INV-1001 | B11: Oak Health Group | C11: 45729 | D11: 45759 | E11: 45771 | F11: East | G11: Imaging | H11: 1804.67 | I11: 1804.67 | J11: Paid | K11: No | L11: None | M11: A. Lopez
A12: INV-1123 | B12: Parkview Internal Medicine | C12: 45729 | D12: 45759 | E12: 45781 | F12: Central | G12: RCM Consulting | H12: 8339 | I12: 8339 | J12: Paid | K12: Yes | L12: Missing info | M12: M. Diaz
A13: INV-1065 | B13: Westgate Family Health | C13: 45730 | D13: 45760 | E13: 45767 | F13: West | G13: RCM Consulting | H13: 6371.4 | I13: 6371.4 | J13: Paid | K13: No | L13: None | M13: S. Patel
A14: INV-1190 | B14: Pioneer Care | C14: 45732 | D14: 45762 | E14: 45763 | F14: South | G14: RCM Consulting | H14: 7294.23 | I14: 7294.23 | J14: Paid | K14: Yes | L14: Eligibility issue | M14: R. Nguyen
A15: INV-1010 | B15: Summit Health | C15: 45733 | D15: 45763 | F15: East | G15: Claims Review | H15: 764.75 | I15: 0 | J15: Unpaid | K15: Yes | L15: Eligibility issue | M15: M. Diaz
A16: INV-1233 | B16: Pioneer Care | C16: 45735 | D16: 45765 | F16: West | G16: Claims Review | H16: 4246.43 | I16: 0 | J16: Unpaid | K16: No | L16: None | M16: A. Lopez
A17: INV-1094 | B17: Red Oak Wellness | C17: 45737 | D17: 45767 | F17: South | G17: Claims Review | H17: 3106.04 | I17: 0 | J17: Unpaid | K17: Yes | L17: Coding issue | M17: S. Patel
A18: INV-1181 | B18: Trinity Wellness | C18: 45739 | D18: 45769 | E18: 45776 | F18: East | G18: RCM Consulting | H18: 7545.37 | I18: 7545.37 | J18: Paid | K18: No | L18: None | M18: M. Diaz
A19: INV-1253 | B19: Summit Health | C19: 45739 | D19: 45769 | F19: West | G19: Claims Review | H19: 2659.04 | I19: 888.34 | J19: Partial | K19: No | L19: None | M19: A. Lopez
A20: INV-1110 | B20: NorthStar Clinic | C20: 45740 | D20: 45770 | E20: 45774 | F20: East | G20: Lab Services | H20: 1511.24 | I20: 1511.24 | J20: Paid | K20: No | L20: None | M20: M. Diaz
A21: INV-1203 | B21: Metro Family Care | C21: 45740 | D21: 45770 | E21: 45749 | F21: Central | G21: Billing Support | H21: 763.78 | I21: 763.78 | J21: Paid | K21: No | L21: None | M21: R. Nguyen
A22: INV-1066 | B22: Pioneer Care | C22: 45742 | D22: 45772 | E22: 45774 | F22: East | G22: Claims Review | H22: 1346.64 | I22: 1346.64 | J22: Paid | K22: No | L22: None | M22: M. Diaz
A23: INV-1083 | B23: Blue Ridge Medical | C23: 45744 | D23: 45774 | E23: 45758 | F23: Central | G23: Billing Support | H23: 2377 | I23: 2377 | J23: Paid | K23: No | L23: None | M23: R. Nguyen
A24: INV-1156 | B24: Red Oak Wellness | C24: 45745 | D24: 45775 | E24: 45757 | F24: East | G24: RCM Consulting | H24: 3621.18 | I24: 3621.18 | J24: Paid | K24: Yes | L24: Eligibility issue | M24: J. Smith
A25: INV-1245 | B25: Riverside Health | C25: 45745 | D25: 45775 | E25: 45796 | F25: West | G25: Imaging | H25: 3791.06 | I25: 3791.06 | J25: Paid | K25: No | L25: None | M25: S. Patel
A26: INV-1161 | B26: Cedar Grove Health | C26: 45750 | D26: 45780 | E26: 45800 | F26: East | G26: Lab Services | H26: 2502.98 | I26: 2502.98 | J26: Paid | K26: No | L26: None | M26: S. Patel
A27: INV-1138 | B27: Parkview Internal Medicine | C27: 45751 | D27: 45781 | E27: 45805 | F27: North | G27: Lab Services | H27: 1738.82 | I27: 1015.16 | J27: Partial | K27: Yes | L27: Denied claim | M27: J. Smith
A28: INV-1180 | B28: Lakeside Imaging | C28: 45751 | D28: 45781 | E28: 45780 | F28: East | G28: Imaging | H28: 5531.15 | I28: 5531.15 | J28: Paid | K28: No | L28: None | M28: R. Nguyen
A29: INV-1091 | B29: Trinity Wellness | C29: 45753 | D29: 45783 | E29: 45803 | F29: North | G29: Imaging | H29: 5084.32 | I29: 2610.76 | J29: Partial | K29: No | L29: None | M29: M. Diaz
A30: INV-1086 | B30: Valley Care Center | C30: 45760 | D30: 45790 | E30: 45782 | F30: South | G30: Lab Services | H30: 2769.77 | I30: 2769.77 | J30: Paid | K30: No | L30: None | M30: S. Patel
A31: INV-1013 | B31: Parkview Internal Medicine | C31: 45763 | D31: 45793 | E31: 45834 | F31: North | G31: Lab Services | H31: 2345.08 | I31: 1127.66 | J31: Partial | K31: Yes | L31: Underpayment | M31: A. Lopez
... A39: INV-1100 | B39: Riverside Health | C39: 45777 | D39: 45807 | E39: 45807 | F39: South | G39: Claims Review | H39: 1667.45 | I39: 1397.57 | J39: Partial | K39: Yes | L39: Coding issue | M39: R. Nguyen
A40: INV-1214 | B40: Canyon Creek Medical | C40: 45777 | D40: 45807 | F40: South | G40: Lab Services | H40: 1556.91 | I40: 0 | J40: Unpaid | K40: Yes | L40: Eligibility issue | M40: K. Brown
A41: INV-1099 | B41: Parkview Internal Medicine | C41: 45779 | D41: 45809 | E41: 45805 | F41: North | G41: Revenue Audit | H41: 4936.36 | I41: 2869.76 | J41: Partial | K41: Yes | L41: Underpayment | M41: S. Patel
A42: INV-1194 | B42: Horizon Medical | C42: 45779 | D42: 45809 | F42: South | G42: Lab Services | H42: 935.23 | I42: 688.62 | J42: Partial | K42: No | L42: None | M42: K. Brown
A43: INV-1171 | B43: Hillcrest Diagnostics | C43: 45780 | D43: 45810 | F43: East | G43: Lab Services | H43: 1245.65 | I43: 0 | J43: Unpaid | K43: Yes | L43: Missing info | M43: A. Lopez
A44: INV-1019 | B44: Westgate Family Health | C44: 45781 | D44: 45811 | E44: 45827 | F44: South | G44: Revenue Audit | H44: 5718.3 | I44: 5718.3 | J44: Paid | K44: No | L44: None | M44: K. Brown
A45: INV-1148 | B45: Pioneer Care | C45: 45783 | D45: 45813 | E45: 45813 | F45: West | G45: RCM Consulting | H45: 2994.86 | I45: 2994.86 | J45: Paid | K45: No | L45: None | M45: R. Nguyen
A46: INV-1131 | B46: NorthStar Clinic | C46: 45784 | D46: 45814 | E46: 45800 | F46: North | G46: Billing Support | H46: 1595.48 | I46: 1595.48 | J46: Paid | K46: No | L46: None | M46: A. Lopez
A47: INV-1170 | B47: Canyon Creek Medical | C47: 45787 | D47: 45817 | E47: 45840 | F47: East | G47: Lab Services | H47: 1889.83 | I47: 1889.83 | J47: Paid | K47: No | L47: None | M47: R. Nguyen
A48: INV-1192 | B48: Red Oak Wellness | C48: 45787 | D48: 45817 | E48: 45796 | F48: Central | G48: Billing Support | H48: 991.65 | I48: 991.65 | J48: Paid | K48: No | L48: None | M48: K. Brown
A49: INV-1162 | B49: Canyon Creek Medical | C49: 45793 | D49: 45823 | F49: East | G49: Lab Services | H49: 2457.2 | I49: 0 | J49: Unpaid | K49: Yes | L49: Missing info | M49: S. Patel
A50: INV-1069 | B50: Canyon Creek Medical | C50: 45795 | D50: 45825 | E50: 45847 | F50: South | G50: Imaging | H50: 5620.1 | I50: 5620.1 | J50: Paid | K50: No | L50: None | M50: K. Brown
A51: INV-1200 | B51: Hillcrest Diagnostics | C51: 45795 | D51: 45825 | E51: 45839 | F51: East | G51: Imaging | H51: 3123.16 | I51: 2457.79 | J51: Partial | K51: Yes | L51: Late payment | M51: A. Lopez
A52: INV-1038 | B52: Westgate Family Health | C52: 45796 | D52: 45826 | E52: 45820 | F52: East | G52: Billing Support | H52: 763.39 | I52: 763.39 | J52: Paid | K52: No | L52: None | M52: S. Patel
A53: INV-1015 | B53: Sunrise Medical Partners | C53: 45797 | D53: 45827 | E53: 45816 | F53: West | G53: Lab Services | H53: 3115.14 | I53: 3115.14 | J53: Paid | K53: No | L53: None | M53: R. Nguyen
A54: INV-1031 | B54: Hillcrest Diagnostics | C54: 45797 | D54: 45827 | E54: 45830 | F54: North | G54: RCM Consulting | H54: 7840.47 | I54: 7840.47 | J54: Paid | K54: Yes | L54: Duplicate invoice | M54: J. Smith
A55: INV-1036 | B55: Valley Care Center | C55: 45797 | D55: 45827 | F55: West | G55: RCM Consulting | H55: 3559.63 | I55: 0 | J55: Unpaid | K55: No | L55: None | M55: R. Nguyen
A56: INV-1058 | B56: Riverside Health | C56: 45798 | D56: 45828 | E56: 45866 | F56: West | G56: Claims Review | H56: 3507.11 | I56: 1896.5 | J56: Partial | K56: Yes | L56: Late payment | M56: M. Diaz
A57: INV-1008 | B57: Lakeside Imaging | C57: 45800 | D57: 45830 | E57: 45843 | F57: East | G57: Billing Support | H57: 1774.39 | I57: 519.62 | J57: Partial | K57: No | L57: None | M57: A. Lopez
A58: INV-1120 | B58: Prime Family Clinic | C58: 45801 | D58: 45831 | E58: 45813 | F58: East | G58: Claims Review | H58: 3486.24 | I58: 3486.24 | J58: Paid | K58: No | L58: None | M58: M. Diaz
A59: INV-1167 | B59: Canyon Creek Medical | C59: 45801 | D59: 45831 | E59: 45870 | F59: West | G59: Lab Services | H59: 1529.33 | I59: 942.61 | J59: Partial | K59: No | L59: None | M59: K. Brown
A60: INV-1154 | B60: Metro Family Care | C60: 45807 | D60: 45837 | E60: 45851 | F60: West | G60: Claims Review | H60: 3539.51 | I60: 3539.51 | J60: Paid | K60: No | L60: None | M60: S. Patel
A61: INV-1047 | B61: Prime Family Clinic | C61: 45808 | D61: 45838 | E61: 45836 | F61: Central | G61: Billing Support | H61: 538.49 | I61: 538.49 | J61: Paid | K61: No | L61: None | M61: J. Smith
A62: INV-1249 | B62: Oak Health Group | C62: 45808 | D62: 45838 | F62: Central | G62: Claims Review | H62: 1009.39 | I62: 0 | J62: Unpaid | K62: No | L62: None | M62: S. Patel
A63: INV-1187 | B63: Canyon Creek Medical | C63: 45809 | D63: 45839 | E63: 45845 | F63: Central | G63: Billing Support | H63: 525.72 | I63: 525.72 | J63: Paid | K63: No | L63: None | M63: M. Diaz
A64: INV-1178 | B64: Sunrise Medical Partners | C64: 45812 | D64: 45842 | E64: 45852 | F64: North | G64: RCM Consulting | H64: 1727.9 | I64: 1727.9 | J64: Paid | K64: No | L64: None | M64: M. Diaz
A65: INV-1101 | B65: Evergreen Pediatrics | C65: 45814 | D65: 45844 | F65: Central | G65: RCM Consulting | H65: 8058.74 | I65: 0 | J65: Unpaid | K65: Yes | L65: Missing info | M65: R. Nguyen
A66: INV-1221 | B66: Oak Health Group | C66: 45814 | D66: 45844 | E66: 45854 | F66: North | G66: Claims Review | H66: 2175.12 | I66: 2175.12 | J66: Paid | K66: No | L66: None | M66: M. Diaz
A67: INV-1215 | B67: Trinity Wellness | C67: 45818 | D67: 45848 | E67: 45847 | F67: Central | G67: RCM Consulting | H67: 5100.61 | I67: 5100.61 | J67: Paid | K67: No | L67: None | M67: K. Brown
A68: INV-1183 | B68: Blue Ridge Medical | C68: 45819 | D68: 45849 | F68: North | G68: Billing Support | H68: 1433.84 | I68: 0 | J68: Unpaid | K68: Yes | L68: Eligibility issue | M68: M. Diaz
A69: INV-1228 | B69: Horizon Medical | C69: 45820 | D69: 45850 | E69: 45865 | F69: Central | G69: Billing Support | H69: 1831.58 | I69: 1831.58 | J69: Paid | K69: No | L69: None | M69: S. Patel
A70: INV-1061 | B70: Blue Ridge Medical | C70: 45822 | D70: 45852 | E70: 45866 | F70: West | G70: Claims Review | H70: 4284.25 | I70: 4284.25 | J70: Paid | K70: No | L70: None | M70: S. Patel
A71: INV-1042 | B71: Lakeside Imaging | C71: 45824 | D71: 45854 | E71: 45871 | F71: South | G71: Revenue Audit | H71: 2574.5 | I71: 2574.5 | J71: Paid | K71: No | L71: None | M71: J. Smith
A72: INV-1020 | B72: Sunrise Medical Partners | C72: 45825 | D72: 45855 | E72: 45874 | F72: Central | G72: Revenue Audit | H72: 1766.1 | I72: 1766.1 | J72: Paid | K72: No | L72: None | M72: R. Nguyen
A73: INV-1030 | B73: Valley Care Center | C73: 45828 | D73: 45858 | F73: North | G73: RCM Consulting | H73: 5429.12 | I73: 2910.41 | J73: Partial | K73: Yes | L73: Late payment | M73: R. Nguyen
A74: INV-1172 | B74: Metro Family Care | C74: 45830 | D74: 45860 | E74: 45862 | F74: West | G74: Billing Support | H74: 1212.77 | I74: 1212.77 | J74: Paid | K74: No | L74: None | M74: J. Smith
A75: INV-1241 | B75: Canyon Creek Medical | C75: 45830 | D75: 45860 | E75: 45902 | F75: South | G75: Imaging | H75: 1902.94 | I75: 950.53 | J75: Partial | K75: No | L75: None | M75: K. Brown
A76: INV-1054 | B76: Valley Care Center | C76: 45832 | D76: 45862 | F76: South | G76: Imaging | H76: 1132.74 | I76: 0 | J76: Unpaid | K76: Yes | L76: Denied claim | M76: J. Smith
A77: INV-1121 | B77: Trinity Wellness | C77: 45832 | D77: 45862 | E77: 45847 | F77: West | G77: RCM Consulting | H77: 1904.36 | I77: 1904.36 | J77: Paid | K77: No | L77: None | M77: M. Diaz
A78: INV-1141 | B78: Red Oak Wellness | C78: 45832 | D78: 45862 | E78: 45883 | F78: West | G78: RCM Consulting | H78: 5985.87 | I78: 1600.45 | J78: Partial | K78: Yes | L78: Missing info | M78: S. Patel
A79: INV-1165 | B79: Horizon Medical | C79: 45832 | D79: 45862 | F79: South | G79: Imaging | H79: 2929.7 | I79: 2200.42 | J79: Partial | K79: Yes | L79: Late payment | M79: J. Smith
A80: INV-1232 | B80: Red Oak Wellness | C80: 45835 | D80: 45865 | E80: 45869 | F80: Central | G80: Revenue Audit | H80: 5206.77 | I80: 5206.77 | J80: Paid | K80: No | L80: None | M80: R. Nguyen
A81: INV-1125 | B81: Oak Health Group | C81: 45837 | D81: 45867 | E81: 45868 | F81: Central | G81: Imaging | H81: 4066.24 | I81: 3324.49 | J81: Partial | K81: No | L81: None | M81: K. Brown
A82: INV-1023 | B82: Hillcrest Diagnostics | C82: 45838 | D82: 45868 | E82: 45882 | F82: East | G82: Revenue Audit | H82: 1835.46 | I82: 1835.46 | J82: Paid | K82: No | L82: None | M82: K. Brown
A83: INV-1043 | B83: Trinity Wellness | C83: 45838 | D83: 45868 | F83: South | G83: Imaging | H83: 978.46 | I83: 715.59 | J83: Partial | K83: Yes | L83: Coding issue | M83: K. Brown
A84: INV-1018 | B84: Valley Care Center | C84: 45839 | D84: 45869 | E84: 45851 | F84: North | G84: Imaging | H84: 7618.04 | I84: 7618.04 | J84: Paid | K84: No | L84: None | M84: S. Patel
A85: INV-1252 | B85: NorthStar Clinic | C85: 45840 | D85: 45870 | E85: 45851 | F85: South | G85: Lab Services | H85: 2241.23 | I85: 2241.23 | J85: Paid | K85: No | L85: None | M85: J. Smith
A86: INV-1229 | B86: Summit Health | C86: 45841 | D86: 45871 | E86: 45870 | F86: North | G86: Revenue Audit | H86: 1896.06 | I86: 1896.06 | J86: Paid | K86: No | L86: None | M86: S. Patel
A87: INV-1026 | B87: Oak Health Group | C87: 45844 | D87: 45874 | E87: 45867 | F87: South | G87: Imaging | H87: 4030.02 | I87: 4030.02 | J87: Paid | K87: No | L87: None | M87: S. Patel
A88: INV-1014 | B88: Hillcrest Diagnostics | C88: 45845 | D88: 45875 | E88: 45894 | F88: Central | G88: Lab Services | H88: 2634.24 | I88: 1873.36 | J88: Partial | K88: Yes | L88: Missing info | M88: R. Nguyen
A89: INV-1077 | B89: Lakeside Imaging | C89: 45849 | D89: 45879 | E89: 45862 | F89: East | G89: Billing Support | H89: 1842.6 | I89: 1842.6 | J89: Paid | K89: Yes | L89: Duplicate invoice | M89: S. Patel
A90: INV-1012 | B90: Westgate Family Health | C90: 45851 | D90: 45881 | E90: 45891 | F90: Central | G90: Claims Review | H90: 2097.6 | I90: 2097.6 | J90: Paid | K90: No | L90: None | M90: S. Patel
A91: INV-1029 | B91: Evergreen Pediatrics | C91: 45852 | D91: 45882 | E91: 45888 | F91: West | G91: Billing Support | H91: 1832.5 | I91: 1185.85 | J91: Partial | K91: No | L91: None | M91: K. Brown
A92: INV-1212 | B92: Trinity Wellness | C92: 45852 | D92: 45882 | E92: 45883 | F92: East | G92: Claims Review | H92: 680.97 | I92: 680.97 | J92: Paid | K92: No | L92: None | M92: M. Diaz
A93: INV-1044 | B93: Summit Health | C93: 45853 | D93: 45883 | E93: 45873 | F93: South | G93: Revenue Audit | H93: 2727.47 | I93: 2727.47 | J93: Paid | K93: No | L93: None | M93: J. Smith
A94: INV-1092 | B94: Evergreen Pediatrics | C94: 45856 | D94: 45886 | E94: 45911 | F94: Central | G94: RCM Consulting | H94: 4614.52 | I94: 4614.52 | J94: Paid | K94: No | L94: None | M94: K. Brown
A95: INV-1116 | B95: Evergreen Pediatrics | C95: 45857 | D95: 45887 | F95: North | G95: RCM Consulting | H95: 7270.83 | I95: 0 | J95: Unpaid | K95: No | L95: None | M95: R. Nguyen
A96: INV-1255 | B96: Valley Care Center | C96: 45857 | D96: 45887 | F96: North | G96: RCM Consulting | H96: 8061.77 | I96: 0 | J96: Unpaid | K96: Yes | L96: Missing info | M96: S. Patel
A97: INV-1076 | B97: Metro Family Care | C97: 45859 | D97: 45889 | E97: 45898 | F97: West | G97: Imaging | H97: 4902.92 | I97: 3729.02 | J97: Partial | K97: Yes | L97: Coding issue | M97: K. Brown
A98: INV-1082 | B98: Canyon Creek Medical | C98: 45861 | D98: 45891 | E98: 45886 | F98: North | G98: Imaging | H98: 2437.88 | I98: 2437.88 | J98: Paid | K98: Yes | L98: Duplicate invoice | M98: M. Diaz
A99: INV-1211 | B99: Blue Ridge Medical | C99: 45861 | D99: 45891 | E99: 45896 | F99: West | G99: RCM Consulting | H99: 6445.66 | I99: 6445.66 | J99: Paid | K99: Yes | L99: Coding issue | M99: R. Nguyen
A100: INV-1059 | B100: Metro Family Care | C100: 45863 | D100: 45893 | E100: 45885 | F100: South | G100: Billing Support | H100: 1003.36 | I100: 1003.36 | J100: Paid | K100: No | L100: None | M100: M. Diaz
A101: INV-1117 | B101: Parkview Internal Medicine | C101: 45863 | D101: 45893 | E101: 45917 | F101: South | G101: RCM Consulting | H101: 2908.24 | I101: 2908.24 | J101: Paid | K101: No | L101: None | M101: M. Diaz
A102: INV-1213 | B102: Westgate Family Health | C102: 45864 | D102: 45894 | E102: 45911 | F102: North | G102: Claims Review | H102: 2301.42 | I102: 2301.42 | J102: Paid | K102: No | L102: None | M102: S. Patel
A103: INV-1226 | B103: Prime Family Clinic | C103: 45864 | D103: 45894 | F103: North | G103: RCM Consulting | H103: 5436.89 | I103: 0 | J103: Unpaid | K103: Yes | L103: Eligibility issue | M103: R. Nguyen
A104: INV-1227 | B104: Trinity Wellness | C104: 45865 | D104: 45895 | F104: North | G104: Billing Support | H104: 473.86 | I104: 0 | J104: Unpaid | K104: Yes | L104: Missing info | M104: R. Nguyen
A105: INV-1236 | B105: Cedar Grove Health | C105: 45868 | D105: 45898 | F105: Central | G105: Revenue Audit | H105: 1630.12 | I105: 0 | J105: Unpaid | K105: No | L105: None | M105: A. Lopez
A106: INV-1205 | B106: Evergreen Pediatrics | C106: 45869 | D106: 45899 | E106: 45890 | F106: West | G106: Lab Services | H106: 585.73 | I106: 585.73 | J106: Paid | K106: No | L106: None | M106: R. Nguyen
A107: INV-1250 | B107: NorthStar Clinic | C107: 45869 | D107: 45899 | E107: 45892 | F107: West | G107: Revenue Audit | H107: 3585.56 | I107: 3585.56 | J107: Paid | K107: No | L107: None | M107: R. Nguyen
...

Sheet Cleaned_Data
A1: Invoice_ID | B1: Customer_Name | C1: Invoice_Date | D1: Due_Date | E1: Payment_Date | F1: Region | G1: Service_Category | H1: Billed_Amount | I1: Paid_Amount | J1: Payment_Status | K1: Denial_or_Exception | L1: Exception_Reason | M1: Account_Manager | N1: Outstanding_Balance | O1: Days_to_Pay | P1: Days_Past_Due | Q1: Aging_Bucket | R1: Month | S1: Year_Month
A2: INV-1017 | B2: Hillcrest Diagnostics | C2: 45717 | D2: 45747 | F2: Central | G2: Billing Support | H2: 342.85 | I2: 0 | J2: Unpaid | K2: No | L2: None | M2: K. Brown | N2: =H2-I2 -> 342.85 | O2: =IF(E2="","",E2-C2) | P2: =IF(N2<=0,0,TODAY()-D2) -> 350 | Q2: =IF(N2<=0,"Paid",IF(P2<=0,"Current",IF(P2<=30,"1-30",IF(P2<=60,"31-60",IF(P2<=90,"61-90","90+"))))) -> 90+ | R2: =TEXT(C2,"mmm") -> Mar | S2: =TEXT(C2,"yyyy-mm") -> 2025-03
A3: INV-1022 | B3: Summit Health | C3: 45720 | D3: 45750 | E3: 45732 | F3: North | G3: Revenue Audit | H3: 1012.03 | I3: 1012.03 | J3: Paid | K3: Yes | L3: Eligibility issue | M3: R. Nguyen | N3: =H3-I3 -> 0 | O3: =IF(E3="","",E3-C3) -> 12 | P3: =IF(N3<=0,0,TODAY()-D3) -> 0 | Q3: =IF(N3<=0,"Paid",IF(P3<=0,"Current",IF(P3<=30,"1-30",IF(P3<=60,"31-60",IF(P3<=90,"61-90","90+"))))) -> Paid | R3: =TEXT(C3,"mmm") -> Mar | S3: =TEXT(C3,"yyyy-mm") -> 2025-03
A4: INV-1238 | B4: Summit Health | C4: 45720 | D4: 45750 | E4: 45765 | F4: East | G4: Claims Review | H4: 2286.94 | I4: 2286.94 | J4: Paid | K4: No | L4: None | M4: A. Lopez | N4: =H4-I4 -> 0 | O4: =IF(E4="","",E4-C4) -> 45 | P4: =IF(N4<=0,0,TODAY()-D4) -> 0 | Q4: =IF(N4<=0,"Paid",IF(P4<=0,"Current",IF(P4<=30,"1-30",IF(P4<=60,"31-60",IF(P4<=90,"61-90","90+"))))) -> Paid | R4: =TEXT(C4,"mmm") -> Mar | S4: =TEXT(C4,"yyyy-mm") -> 2025-03
A5: INV-1037 | B5: Hillcrest Diagnostics | C5: 45721 | D5: 45751 | F5: Central | G5: Billing Support | H5: 527.89 | I5: 0 | J5: Unpaid | K5: Yes | L5: Denied claim | M5: R. Nguyen | N5: =H5-I5 -> 527.89 | O5: =IF(E5="","",E5-C5) | P5: =IF(N5<=0,0,TODAY()-D5) -> 346 | Q5: =IF(N5<=0,"Paid",IF(P5<=0,"Current",IF(P5<=30,"1-30",IF(P5<=60,"31-60",IF(P5<=90,"61-90","90+"))))) -> 90+ | R5: =TEXT(C5,"mmm") -> Mar | S5: =TEXT(C5,"yyyy-mm") -> 2025-03
A6: INV-1234 | B6: Blue Ridge Medical | C6: 45721 | D6: 45751 | F6: East | G6: RCM Consulting | H6: 2036.95 | I6: 0 | J6: Unpaid | K6: Yes | L6: Coding issue | M6: S. Patel | N6: =H6-I6 -> 2036.95 | O6: =IF(E6="","",E6-C6) | P6: =IF(N6<=0,0,TODAY()-D6) -> 346 | Q6: =IF(N6<=0,"Paid",IF(P6<=0,"Current",IF(P6<=30,"1-30",IF(P6<=60,"31-60",IF(P6<=90,"61-90","90+"))))) -> 90+ | R6: =TEXT(C6,"mmm") -> Mar | S6: =TEXT(C6,"yyyy-mm") -> 2025-03
A7: INV-1239 | B7: Red Oak Wellness | C7: 45722 | D7: 45752 | E7: 45749 | F7: East | G7: Revenue Audit | H7: 4371.67 | I7: 4371.67 | J7: Paid | K7: No | L7: None | M7: M. Diaz | N7: =H7-I7 -> 0 | O7: =IF(E7="","",E7-C7) -> 27 | P7: =IF(N7<=0,0,TODAY()-D7) -> 0 | Q7: =IF(N7<=0,"Paid",IF(P7<=0,"Current",IF(P7<=30,"1-30",IF(P7<=60,"31-60",IF(P7<=90,"61-90","90+"))))) -> Paid | R7: =TEXT(C7,"mmm") -> Mar | S7: =TEXT(C7,"yyyy-mm") -> 2025-03
A8: INV-1179 | B8: Westgate Family Health | C8: 45727 | D8: 45757 | F8: West | G8: Claims Review | H8: 3042.68 | I8: 0 | J8: Unpaid | K8: Yes | L8: Denied claim | M8: J. Smith | N8: =H8-I8 -> 3042.68 | O8: =IF(E8="","",E8-C8) | P8: =IF(N8<=0,0,TODAY()-D8) -> 340 | Q8: =IF(N8<=0,"Paid",IF(P8<=0,"Current",IF(P8<=30,"1-30",IF(P8<=60,"31-60",IF(P8<=90,"61-90","90+"))))) -> 90+ | R8: =TEXT(C8,"mmm") -> Mar | S8: =TEXT(C8,"yyyy-mm") -> 2025-03
A9: INV-1210 | B9: Parkview Internal Medicine | C9: 45728 | D9: 45758 | E9: 45739 | F9: North | G9: Claims Review | H9: 2328.92 | I9: 2328.92 | J9: Paid | K9: No | L9: None | M9: S. Patel | N9: =H9-I9 -> 0 | O9: =IF(E9="","",E9-C9) -> 11 | P9: =IF(N9<=0,0,TODAY()-D9) -> 0 | Q9: =IF(N9<=0,"Paid",IF(P9<=0,"Current",IF(P9<=30,"1-30",IF(P9<=60,"31-60",IF(P9<=90,"61-90","90+"))))) -> Paid | R9: =TEXT(C9,"mmm") -> Mar | S9: =TEXT(C9,"yyyy-mm") -> 2025-03
A10: INV-1246 | B10: Valley Care Center | C10: 45728 | D10: 45758 | E10: 45780 | F10: West | G10: Billing Support | H10: 1940.77 | I10: 1940.77 | J10: Paid | K10: Yes | L10: Eligibility issue | M10: J. Smith | N10: =H10-I10 -> 0 | O10: =IF(E10="","",E10-C10) -> 52 | P10: =IF(N10<=0,0,TODAY()-D10) -> 0 | Q10: =IF(N10<=0,"Paid",IF(P10<=0,"Current",IF(P10<=30,"1-30",IF(P10<=60,"31-60",IF(P10<=90,"61-90","90+"))))) -> Paid | R10: =TEXT(C10,"mmm") -> Mar | S10: =TEXT(C10,"yyyy-mm") -> 2025-03
A11: INV-1001 | B11: Oak Health Group | C11: 45729 | D11: 45759 | E11: 45771 | F11: East | G11: Imaging | H11: 1804.67 | I11: 1804.67 | J11: Paid | K11: No | L11: None | M11: A. Lopez | N11: =H11-I11 -> 0 | O11: =IF(E11="","",E11-C11) -> 42 | P11: =IF(N11<=0,0,TODAY()-D11) -> 0 | Q11: =IF(N11<=0,"Paid",IF(P11<=0,"Current",IF(P11<=30,"1-30",IF(P11<=60,"31-60",IF(P11<=90,"61-90","90+"))))) -> Paid | R11: =TEXT(C11,"mmm") -> Mar | S11: =TEXT(C11,"yyyy-mm") -> 2025-03
A12: INV-1123 | B12: Parkview Internal Medicine | C12: 45729 | D12: 45759 | E12: 45781 | F12: Central | G12: RCM Consulting | H12: 8339 | I12: 8339 | J12: Paid | K12: Yes | L12: Missing info | M12: M. Diaz | N12: =H12-I12 -> 0 | O12: =IF(E12="","",E12-C12) -> 52 | P12: =IF(N12<=0,0,TODAY()-D12) -> 0 | Q12: =IF(N12<=0,"Paid",IF(P12<=0,"Current",IF(P12<=30,"1-30",IF(P12<=60,"31-60",IF(P12<=90,"61-90","90+"))))) -> Paid | R12: =TEXT(C12,"mmm") -> Mar | S12: =TEXT(C12,"yyyy-mm") -> 2025-03
A13: INV-1065 | B13: Westgate Family Health | C13: 45730 | D13: 45760 | E13: 45767 | F13: West | G13: RCM Consulting | H13: 6371.4 | I13: 6371.4 | J13: Paid | K13: No | L13: None | M13: S. Patel | N13: =H13-I13 -> 0 | O13: =IF(E13="","",E13-C13) -> 37 | P13: =IF(N13<=0,0,TODAY()-D13) -> 0 | Q13: =IF(N13<=0,"Paid",IF(P13<=0,"Current",IF(P13<=30,"1-30",IF(P13<=60,"31-60",IF(P13<=90,"61-90","90+"))))) -> Paid | R13: =TEXT(C13,"mmm") -> Mar | S13: =TEXT(C13,"yyyy-mm") -> 2025-03
A14: INV-1190 | B14: Pioneer Care | C14: 45732 | D14: 45762 | E14: 45763 | F14: South | G14: RCM Consulting | H14: 7294.23 | I14: 7294.23 | J14: Paid | K14: Yes | L14: Eligibility issue | M14: R. Nguyen | N14: =H14-I14 -> 0 | O14: =IF(E14="","",E14-C14) -> 31 | P14: =IF(N14<=0,0,TODAY()-D14) -> 0 | Q14: =IF(N14<=0,"Paid",IF(P14<=0,"Current",IF(P14<=30,"1-30",IF(P14<=60,"31-60",IF(P14<=90,"61-90","90+"))))) -> Paid | R14: =TEXT(C14,"mmm") -> Mar | S14: =TEXT(C14,"yyyy-mm") -> 2025-03
A15: INV-1010 | B15: Summit Health | C15: 45733 | D15: 45763 | F15: East | G15: Claims Review | H15: 764.75 | I15: 0 | J15: Unpaid | K15: Yes | L15: Eligibility issue | M15: M. Diaz | N15: =H15-I15 -> 764.75 | O15: =IF(E15="","",E15-C15) | P15: =IF(N15<=0,0,TODAY()-D15) -> 334 | Q15: =IF(N15<=0,"Paid",IF(P15<=0,"Current",IF(P15<=30,"1-30",IF(P15<=60,"31-60",IF(P15<=90,"61-90","90+"))))) -> 90+ | R15: =TEXT(C15,"mmm") -> Mar | S15: =TEXT(C15,"yyyy-mm") -> 2025-03
A16: INV-1233 | B16: Pioneer Care | C16: 45735 | D16: 45765 | F16: West | G16: Claims Review | H16: 4246.43 | I16: 0 | J16: Unpaid | K16: No | L16: None | M16: A. Lopez | N16: =H16-I16 -> 4246.43 | O16: =IF(E16="","",E16-C16) | P16: =IF(N16<=0,0,TODAY()-D16) -> 332 | Q16: =IF(N16<=0,"Paid",IF(P16<=0,"Current",IF(P16<=30,"1-30",IF(P16<=60,"31-60",IF(P16<=90,"61-90","90+"))))) -> 90+ | R16: =TEXT(C16,"mmm") -> Mar | S16: =TEXT(C16,"yyyy-mm") -> 2025-03
A17: INV-1094 | B17: Red Oak Wellness | C17: 45737 | D17: 45767 | F17: South | G17: Claims Review | H17: 3106.04 | I17: 0 | J17: Unpaid | K17: Yes | L17: Coding issue | M17: S. Patel | N17: =H17-I17 -> 3106.04 | O17: =IF(E17="","",E17-C17) | P17: =IF(N17<=0,0,TODAY()-D17) -> 330 | Q17: =IF(N17<=0,"Paid",IF(P17<=0,"Current",IF(P17<=30,"1-30",IF(P17<=60,"31-60",IF(P17<=90,"61-90","90+"))))) -> 90+ | R17: =TEXT(C17,"mmm") -> Mar | S17: =TEXT(C17,"yyyy-mm") -> 2025-03
A18: INV-1181 | B18: Trinity Wellness | C18: 45739 | D18: 45769 | E18: 45776 | F18: East | G18: RCM Consulting | H18: 7545.37 | I18: 7545.37 | J18: Paid | K18: No | L18: None | M18: M. Diaz | N18: =H18-I18 -> 0 | O18: =IF(E18="","",E18-C18) -> 37 | P18: =IF(N18<=0,0,TODAY()-D18) -> 0 | Q18: =IF(N18<=0,"Paid",IF(P18<=0,"Current",IF(P18<=30,"1-30",IF(P18<=60,"31-60",IF(P18<=90,"61-90","90+"))))) -> Paid | R18: =TEXT(C18,"mmm") -> Mar | S18: =TEXT(C18,"yyyy-mm") -> 2025-03
A19: INV-1253 | B19: Summit Health | C19: 45739 | D19: 45769 | F19: West | G19: Claims Review | H19: 2659.04 | I19: 888.34 | J19: Partial | K19: No | L19: None | M19: A. Lopez | N19: =H19-I19 -> 1770.7 | O19: =IF(E19="","",E19-C19) | P19: =IF(N19<=0,0,TODAY()-D19) -> 328 | Q19: =IF(N19<=0,"Paid",IF(P19<=0,"Current",IF(P19<=30,"1-30",IF(P19<=60,"31-60",IF(P19<=90,"61-90","90+"))))) -> 90+ | R19: =TEXT(C19,"mmm") -> Mar | S19: =TEXT(C19,"yyyy-mm") -> 2025-03
A20: INV-1110 | B20: NorthStar Clinic | C20: 45740 | D20: 45770 | E20: 45774 | F20: East | G20: Lab Services | H20: 1511.24 | I20: 1511.24 | J20: Paid | K20: No | L20: None | M20: M. Diaz | N20: =H20-I20 -> 0 | O20: =IF(E20="","",E20-C20) -> 34 | P20: =IF(N20<=0,0,TODAY()-D20) -> 0 | Q20: =IF(N20<=0,"Paid",IF(P20<=0,"Current",IF(P20<=30,"1-30",IF(P20<=60,"31-60",IF(P20<=90,"61-90","90+"))))) -> Paid | R20: =TEXT(C20,"mmm") -> Mar | S20: =TEXT(C20,"yyyy-mm") -> 2025-03
A21: INV-1203 | B21: Metro Family Care | C21: 45740 | D21: 45770 | E21: 45749 | F21: Central | G21: Billing Support | H21: 763.78 | I21: 763.78 | J21: Paid | K21: No | L21: None | M21: R. Nguyen | N21: =H21-I21 -> 0 | O21: =IF(E21="","",E21-C21) -> 9 | P21: =IF(N21<=0,0,TODAY()-D21) -> 0 | Q21: =IF(N21<=0,"Paid",IF(P21<=0,"Current",IF(P21<=30,"1-30",IF(P21<=60,"31-60",IF(P21<=90,"61-90","90+"))))) -> Paid | R21: =TEXT(C21,"mmm") -> Mar | S21: =TEXT(C21,"yyyy-mm") -> 2025-03
A22: INV-1066 | B22: Pioneer Care | C22: 45742 | D22: 45772 | E22: 45774 | F22: East | G22: Claims Review | H22: 1346.64 | I22: 1346.64 | J22: Paid | K22: No | L22: None | M22: M. Diaz | N22: =H22-I22 -> 0 | O22: =IF(E22="","",E22-C22) -> 32 | P22: =IF(N22<=0,0,TODAY()-D22) -> 0 | Q22: =IF(N22<=0,"Paid",IF(P22<=0,"Current",IF(P22<=30,"1-30",IF(P22<=60,"31-60",IF(P22<=90,"61-90","90+"))))) -> Paid | R22: =TEXT(C22,"mmm") -> Mar | S22: =TEXT(C22,"yyyy-mm") -> 2025-03
A23: INV-1083 | B23: Blue Ridge Medical | C23: 45744 | D23: 45774 | E23: 45758 | F23: Central | G23: Billing Support | H23: 2377 | I23: 2377 | J23: Paid | K23: No | L23: None | M23: R. Nguyen | N23: =H23-I23 -> 0 | O23: =IF(E23="","",E23-C23) -> 14 | P23: =IF(N23<=0,0,TODAY()-D23) -> 0 | Q23: =IF(N23<=0,"Paid",IF(P23<=0,"Current",IF(P23<=30,"1-30",IF(P23<=60,"31-60",IF(P23<=90,"61-90","90+"))))) -> Paid | R23: =TEXT(C23,"mmm") -> Mar | S23: =TEXT(C23,"yyyy-mm") -> 2025-03
A24: INV-1156 | B24: Red Oak Wellness | C24: 45745 | D24: 45775 | E24: 45757 | F24: East | G24: RCM Consulting | H24: 3621.18 | I24: 3621.18 | J24: Paid | K24: Yes | L24: Eligibility issue | M24: J. Smith | N24: =H24-I24 -> 0 | O24: =IF(E24="","",E24-C24) -> 12 | P24: =IF(N24<=0,0,TODAY()-D24) -> 0 | Q24: =IF(N24<=0,"Paid",IF(P24<=0,"Current",IF(P24<=30,"1-30",IF(P24<=60,"31-60",IF(P24<=90,"61-90","90+"))))) -> Paid | R24: =TEXT(C24,"mmm") -> Mar | S24: =TEXT(C24,"yyyy-mm") -> 2025-03
A25: INV-1245 | B25: Riverside Health | C25: 45745 | D25: 45775 | E25: 45796 | F25: West | G25: Imaging | H25: 3791.06 | I25: 3791.06 | J25: Paid | K25: No | L25: None | M25: S. Patel | N25: =H25-I25 -> 0 | O25: =IF(E25="","",E25-C25) -> 51 | P25: =IF(N25<=0,0,TODAY()-D25) -> 0 | Q25: =IF(N25<=0,"Paid",IF(P25<=0,"Current",IF(P25<=30,"1-30",IF(P25<=60,"31-60",IF(P25<=90,"61-90","90+"))))) -> Paid | R25: =TEXT(C25,"mmm") -> Mar | S25: =TEXT(C25,"yyyy-mm") -> 2025-03
A26: INV-1161 | B26: Cedar Grove Health | C26: 45750 | D26: 45780 | E26: 45800 | F26: East | G26: Lab Services | H26: 2502.98 | I26: 2502.98 | J26: Paid | K26: No | L26: None | M26: S. Patel | N26: =H26-I26 -> 0 | O26: =IF(E26="","",E26-C26) -> 50 | P26: =IF(N26<=0,0,TODAY()-D26) -> 0 | Q26: =IF(N26<=0,"Paid",IF(P26<=0,"Current",IF(P26<=30,"1-30",IF(P26<=60,"31-60",IF(P26<=90,"61-90","90+"))))) -> Paid | R26: =TEXT(C26,"mmm") -> Apr | S26: =TEXT(C26,"yyyy-mm") -> 2025-04
A27: INV-1138 | B27: Parkview Internal Medicine | C27: 45751 | D27: 45781 | E27: 45805 | F27: North | G27: Lab Services | H27: 1738.82 | I27: 1015.16 | J27: Partial | K27: Yes | L27: Denied claim | M27: J. Smith | N27: =H27-I27 -> 723.66 | O27: =IF(E27="","",E27-C27) -> 54 | P27: =IF(N27<=0,0,TODAY()-D27) -> 316 | Q27: =IF(N27<=0,"Paid",IF(P27<=0,"Current",IF(P27<=30,"1-30",IF(P27<=60,"31-60",IF(P27<=90,"61-90","90+"))))) -> 90+ | R27: =TEXT(C27,"mmm") -> Apr | S27: =TEXT(C27,"yyyy-mm") -> 2025-04
A28: INV-1180 | B28: Lakeside Imaging | C28: 45751 | D28: 45781 | E28: 45780 | F28: East | G28: Imaging | H28: 5531.15 | I28: 5531.15 | J28: Paid | K28: No | L28: None | M28: R. Nguyen | N28: =H28-I28 -> 0 | O28: =IF(E28="","",E28-C28) -> 29 | P28: =IF(N28<=0,0,TODAY()-D28) -> 0 | Q28: =IF(N28<=0,"Paid",IF(P28<=0,"Current",IF(P28<=30,"1-30",IF(P28<=60,"31-60",IF(P28<=90,"61-90","90+"))))) -> Paid | R28: =TEXT(C28,"mmm") -> Apr | S28: =TEXT(C28,"yyyy-mm") -> 2025-04
A29: INV-1091 | B29: Trinity Wellness | C29: 45753 | D29: 45783 | E29: 45803 | F29: North | G29: Imaging | H29: 5084.32 | I29: 2610.76 | J29: Partial | K29: No | L29: None | M29: M. Diaz | N29: =H29-I29 -> 2473.56 | O29: =IF(E29="","",E29-C29) -> 50 | P29: =IF(N29<=0,0,TODAY()-D29) -> 314 | Q29: =IF(N29<=0,"Paid",IF(P29<=0,"Current",IF(P29<=30,"1-30",IF(P29<=60,"31-60",IF(P29<=90,"61-90","90+"))))) -> 90+ | R29: =TEXT(C29,"mmm") -> Apr | S29: =TEXT(C29,"yyyy-mm") -> 2025-04
A30: INV-1086 | B30: Valley Care Center | C30: 45760 | D30: 45790 | E30: 45782 | F30: South | G30: Lab Services | H30: 2769.77 | I30: 2769.77 | J30: Paid | K30: No | L30: None | M30: S. Patel | N30: =H30-I30 -> 0 | O30: =IF(E30="","",E30-C30) -> 22 | P30: =IF(N30<=0,0,TODAY()-D30) -> 0 | Q30: =IF(N30<=0,"Paid",IF(P30<=0,"Current",IF(P30<=30,"1-30",IF(P30<=60,"31-60",IF(P30<=90,"61-90","90+"))))) -> Paid | R30: =TEXT(C30,"mmm") -> Apr | S30: =TEXT(C30,"yyyy-mm") -> 2025-04
A31: INV-1013 | B31: Parkview Internal Medicine | C31: 45763 | D31: 45793 | E31: 45834 | F31: North | G31: Lab Services | H31: 2345.08 | I31: 1127.66 | J31: Partial | K31: Yes | L31: Underpayment | M31: A. Lopez | N31: =H31-I31 -> 1217.42 | O31: =IF(E31="","",E31-C31) -> 71 | P31: =IF(N31<=0,0,TODAY()-D31) -> 304 | Q31: =IF(N31<=0,"Paid",IF(P31<=0,"Current",IF(P31<=30,"1-30",IF(P31<=60,"31-60",IF(P31<=90,"61-90","90+"))))) -> 90+ | R31: =TEXT(C31,"mmm") -> Apr | S31: =TEXT(C31,"yyyy-mm") -> 2025-04
... A39: INV-1100 | B39: Riverside Health | C39: 45777 | D39: 45807 | E39: 45807 | F39: South | G39: Claims Review | H39: 1667.45 | I39: 1397.57 | J39: Partial | K39: Yes | L39: Coding issue | M39: R. Nguyen | N39: =H39-I39 -> 269.88 | O39: =IF(E39="","",E39-C39) -> 30 | P39: =IF(N39<=0,0,TODAY()-D39) -> 290 | Q39: =IF(N39<=0,"Paid",IF(P39<=0,"Current",IF(P39<=30,"1-30",IF(P39<=60,"31-60",IF(P39<=90,"61-90","90+"))))) -> 90+ | R39: =TEXT(C39,"mmm") -> Apr | S39: =TEXT(C39,"yyyy-mm") -> 2025-04
A40: INV-1214 | B40: Canyon Creek Medical | C40: 45777 | D40: 45807 | F40: South | G40: Lab Services | H40: 1556.91 | I40: 0 | J40: Unpaid | K40: Yes | L40: Eligibility issue | M40: K. Brown | N40: =H40-I40 -> 1556.91 | O40: =IF(E40="","",E40-C40) | P40: =IF(N40<=0,0,TODAY()-D40) -> 290 | Q40: =IF(N40<=0,"Paid",IF(P40<=0,"Current",IF(P40<=30,"1-30",IF(P40<=60,"31-60",IF(P40<=90,"61-90","90+"))))) -> 90+ | R40: =TEXT(C40,"mmm") -> Apr | S40: =TEXT(C40,"yyyy-mm") -> 2025-04
A41: INV-1099 | B41: Parkview Internal Medicine | C41: 45779 | D41: 45809 | E41: 45805 | F41: North | G41: Revenue Audit | H41: 4936.36 | I41: 2869.76 | J41: Partial | K41: Yes | L41: Underpayment | M41: S. Patel | N41: =H41-I41 -> 2066.6 | O41: =IF(E41="","",E41-C41) -> 26 | P41: =IF(N41<=0,0,TODAY()-D41) -> 288 | Q41: =IF(N41<=0,"Paid",IF(P41<=0,"Current",IF(P41<=30,"1-30",IF(P41<=60,"31-60",IF(P41<=90,"61-90","90+"))))) -> 90+ | R41: =TEXT(C41,"mmm") -> May | S41: =TEXT(C41,"yyyy-mm") -> 2025-05
A42: INV-1194 | B42: Horizon Medical | C42: 45779 | D42: 45809 | F42: South | G42: Lab Services | H42: 935.23 | I42: 688.62 | J42: Partial | K42: No | L42: None | M42: K. Brown | N42: =H42-I42 -> 246.61 | O42: =IF(E42="","",E42-C42) | P42: =IF(N42<=0,0,TODAY()-D42) -> 288 | Q42: =IF(N42<=0,"Paid",IF(P42<=0,"Current",IF(P42<=30,"1-30",IF(P42<=60,"31-60",IF(P42<=90,"61-90","90+"))))) -> 90+ | R42: =TEXT(C42,"mmm") -> May | S42: =TEXT(C42,"yyyy-mm") -> 2025-05
A43: INV-1171 | B43: Hillcrest Diagnostics | C43: 45780 | D43: 45810 | F43: East | G43: Lab Services | H43: 1245.65 | I43: 0 | J43: Unpaid | K43: Yes | L43: Missing info | M43: A. Lopez | N43: =H43-I43 -> 1245.65 | O43: =IF(E43="","",E43-C43) | P43: =IF(N43<=0,0,TODAY()-D43) -> 287 | Q43: =IF(N43<=0,"Paid",IF(P43<=0,"Current",IF(P43<=30,"1-30",IF(P43<=60,"31-60",IF(P43<=90,"61-90","90+"))))) -> 90+ | R43: =TEXT(C43,"mmm") -> May | S43: =TEXT(C43,"yyyy-mm") -> 2025-05
A44: INV-1019 | B44: Westgate Family Health | C44: 45781 | D44: 45811 | E44: 45827 | F44: South | G44: Revenue Audit | H44: 5718.3 | I44: 5718.3 | J44: Paid | K44: No | L44: None | M44: K. Brown | N44: =H44-I44 -> 0 | O44: =IF(E44="","",E44-C44) -> 46 | P44: =IF(N44<=0,0,TODAY()-D44) -> 0 | Q44: =IF(N44<=0,"Paid",IF(P44<=0,"Current",IF(P44<=30,"1-30",IF(P44<=60,"31-60",IF(P44<=90,"61-90","90+"))))) -> Paid | R44: =TEXT(C44,"mmm") -> May | S44: =TEXT(C44,"yyyy-mm") -> 2025-05
A45: INV-1148 | B45: Pioneer Care | C45: 45783 | D45: 45813 | E45: 45813 | F45: West | G45: RCM Consulting | H45: 2994.86 | I45: 2994.86 | J45: Paid | K45: No | L45: None | M45: R. Nguyen | N45: =H45-I45 -> 0 | O45: =IF(E45="","",E45-C45) -> 30 | P45: =IF(N45<=0,0,TODAY()-D45) -> 0 | Q45: =IF(N45<=0,"Paid",IF(P45<=0,"Current",IF(P45<=30,"1-30",IF(P45<=60,"31-60",IF(P45<=90,"61-90","90+"))))) -> Paid | R45: =TEXT(C45,"mmm") -> May | S45: =TEXT(C45,"yyyy-mm") -> 2025-05
A46: INV-1131 | B46: NorthStar Clinic | C46: 45784 | D46: 45814 | E46: 45800 | F46: North | G46: Billing Support | H46: 1595.48 | I46: 1595.48 | J46: Paid | K46: No | L46: None | M46: A. Lopez | N46: =H46-I46 -> 0 | O46: =IF(E46="","",E46-C46) -> 16 | P46: =IF(N46<=0,0,TODAY()-D46) -> 0 | Q46: =IF(N46<=0,"Paid",IF(P46<=0,"Current",IF(P46<=30,"1-30",IF(P46<=60,"31-60",IF(P46<=90,"61-90","90+"))))) -> Paid | R46: =TEXT(C46,"mmm") -> May | S46: =TEXT(C46,"yyyy-mm") -> 2025-05
A47: INV-1170 | B47: Canyon Creek Medical | C47: 45787 | D47: 45817 | E47: 45840 | F47: East | G47: Lab Services | H47: 1889.83 | I47: 1889.83 | J47: Paid | K47: No | L47: None | M47: R. Nguyen | N47: =H47-I47 -> 0 | O47: =IF(E47="","",E47-C47) -> 53 | P47: =IF(N47<=0,0,TODAY()-D47) -> 0 | Q47: =IF(N47<=0,"Paid",IF(P47<=0,"Current",IF(P47<=30,"1-30",IF(P47<=60,"31-60",IF(P47<=90,"61-90","90+"))))) -> Paid | R47: =TEXT(C47,"mmm") -> May | S47: =TEXT(C47,"yyyy-mm") -> 2025-05
A48: INV-1192 | B48: Red Oak Wellness | C48: 45787 | D48: 45817 | E48: 45796 | F48: Central | G48: Billing Support | H48: 991.65 | I48: 991.65 | J48: Paid | K48: No | L48: None | M48: K. Brown | N48: =H48-I48 -> 0 | O48: =IF(E48="","",E48-C48) -> 9 | P48: =IF(N48<=0,0,TODAY()-D48) -> 0 | Q48: =IF(N48<=0,"Paid",IF(P48<=0,"Current",IF(P48<=30,"1-30",IF(P48<=60,"31-60",IF(P48<=90,"61-90","90+"))))) -> Paid | R48: =TEXT(C48,"mmm") -> May | S48: =TEXT(C48,"yyyy-mm") -> 2025-05
A49: INV-1162 | B49: Canyon Creek Medical | C49: 45793 | D49: 45823 | F49: East | G49: Lab Services | H49: 2457.2 | I49: 0 | J49: Unpaid | K49: Yes | L49: Missing info | M49: S. Patel | N49: =H49-I49 -> 2457.2 | O49: =IF(E49="","",E49-C49) | P49: =IF(N49<=0,0,TODAY()-D49) -> 274 | Q49: =IF(N49<=0,"Paid",IF(P49<=0,"Current",IF(P49<=30,"1-30",IF(P49<=60,"31-60",IF(P49<=90,"61-90","90+"))))) -> 90+ | R49: =TEXT(C49,"mmm") -> May | S49: =TEXT(C49,"yyyy-mm") -> 2025-05
A50: INV-1069 | B50: Canyon Creek Medical | C50: 45795 | D50: 45825 | E50: 45847 | F50: South | G50: Imaging | H50: 5620.1 | I50: 5620.1 | J50: Paid | K50: No | L50: None | M50: K. Brown | N50: =H50-I50 -> 0 | O50: =IF(E50="","",E50-C50) -> 52 | P50: =IF(N50<=0,0,TODAY()-D50) -> 0 | Q50: =IF(N50<=0,"Paid",IF(P50<=0,"Current",IF(P50<=30,"1-30",IF(P50<=60,"31-60",IF(P50<=90,"61-90","90+"))))) -> Paid | R50: =TEXT(C50,"mmm") -> May | S50: =TEXT(C50,"yyyy-mm") -> 2025-05
A51: INV-1200 | B51: Hillcrest Diagnostics | C51: 45795 | D51: 45825 | E51: 45839 | F51: East | G51: Imaging | H51: 3123.16 | I51: 2457.79 | J51: Partial | K51: Yes | L51: Late payment | M51: A. Lopez | N51: =H51-I51 -> 665.37 | O51: =IF(E51="","",E51-C51) -> 44 | P51: =IF(N51<=0,0,TODAY()-D51) -> 272 | Q51: =IF(N51<=0,"Paid",IF(P51<=0,"Current",IF(P51<=30,"1-30",IF(P51<=60,"31-60",IF(P51<=90,"61-90","90+"))))) -> 90+ | R51: =TEXT(C51,"mmm") -> May | S51: =TEXT(C51,"yyyy-mm") -> 2025-05
A52: INV-1038 | B52: Westgate Family Health | C52: 45796 | D52: 45826 | E52: 45820 | F52: East | G52: Billing Support | H52: 763.39 | I52: 763.39 | J52: Paid | K52: No | L52: None | M52: S. Patel | N52: =H52-I52 -> 0 | O52: =IF(E52="","",E52-C52) -> 24 | P52: =IF(N52<=0,0,TODAY()-D52) -> 0 | Q52: =IF(N52<=0,"Paid",IF(P52<=0,"Current",IF(P52<=30,"1-30",IF(P52<=60,"31-60",IF(P52<=90,"61-90","90+"))))) -> Paid | R52: =TEXT(C52,"mmm") -> May | S52: =TEXT(C52,"yyyy-mm") -> 2025-05
A53: INV-1015 | B53: Sunrise Medical Partners | C53: 45797 | D53: 45827 | E53: 45816 | F53: West | G53: Lab Services | H53: 3115.14 | I53: 3115.14 | J53: Paid | K53: No | L53: None | M53: R. Nguyen | N53: =H53-I53 -> 0 | O53: =IF(E53="","",E53-C53) -> 19 | P53: =IF(N53<=0,0,TODAY()-D53) -> 0 | Q53: =IF(N53<=0,"Paid",IF(P53<=0,"Current",IF(P53<=30,"1-30",IF(P53<=60,"31-60",IF(P53<=90,"61-90","90+"))))) -> Paid | R53: =TEXT(C53,"mmm") -> May | S53: =TEXT(C53,"yyyy-mm") -> 2025-05
A54: INV-1031 | B54: Hillcrest Diagnostics | C54: 45797 | D54: 45827 | E54: 45830 | F54: North | G54: RCM Consulting | H54: 7840.47 | I54: 7840.47 | J54: Paid | K54: Yes | L54: Duplicate invoice | M54: J. Smith | N54: =H54-I54 -> 0 | O54: =IF(E54="","",E54-C54) -> 33 | P54: =IF(N54<=0,0,TODAY()-D54) -> 0 | Q54: =IF(N54<=0,"Paid",IF(P54<=0,"Current",IF(P54<=30,"1-30",IF(P54<=60,"31-60",IF(P54<=90,"61-90","90+"))))) -> Paid | R54: =TEXT(C54,"mmm") -> May | S54: =TEXT(C54,"yyyy-mm") -> 2025-05
A55: INV-1036 | B55: Valley Care Center | C55: 45797 | D55: 45827 | F55: West | G55: RCM Consulting | H55: 3559.63 | I55: 0 | J55: Unpaid | K55: No | L55: None | M55: R. Nguyen | N55: =H55-I55 -> 3559.63 | O55: =IF(E55="","",E55-C55) | P55: =IF(N55<=0,0,TODAY()-D55) -> 270 | Q55: =IF(N55<=0,"Paid",IF(P55<=0,"Current",IF(P55<=30,"1-30",IF(P55<=60,"31-60",IF(P55<=90,"61-90","90+"))))) -> 90+ | R55: =TEXT(C55,"mmm") -> May | S55: =TEXT(C55,"yyyy-mm") -> 2025-05
A56: INV-1058 | B56: Riverside Health | C56: 45798 | D56: 45828 | E56: 45866 | F56: West | G56: Claims Review | H56: 3507.11 | I56: 1896.5 | J56: Partial | K56: Yes | L56: Late payment | M56: M. Diaz | N56: =H56-I56 -> 1610.61 | O56: =IF(E56="","",E56-C56) -> 68 | P56: =IF(N56<=0,0,TODAY()-D56) -> 269 | Q56: =IF(N56<=0,"Paid",IF(P56<=0,"Current",IF(P56<=30,"1-30",IF(P56<=60,"31-60",IF(P56<=90,"61-90","90+"))))) -> 90+ | R56: =TEXT(C56,"mmm") -> May | S56: =TEXT(C56,"yyyy-mm") -> 2025-05
A57: INV-1008 | B57: Lakeside Imaging | C57: 45800 | D57: 45830 | E57: 45843 | F57: East | G57: Billing Support | H57: 1774.39 | I57: 519.62 | J57: Partial | K57: No | L57: None | M57: A. Lopez | N57: =H57-I57 -> 1254.77 | O57: =IF(E57="","",E57-C57) -> 43 | P57: =IF(N57<=0,0,TODAY()-D57) -> 267 | Q57: =IF(N57<=0,"Paid",IF(P57<=0,"Current",IF(P57<=30,"1-30",IF(P57<=60,"31-60",IF(P57<=90,"61-90","90+"))))) -> 90+ | R57: =TEXT(C57,"mmm") -> May | S57: =TEXT(C57,"yyyy-mm") -> 2025-05
A58: INV-1120 | B58: Prime Family Clinic | C58: 45801 | D58: 45831 | E58: 45813 | F58: East | G58: Claims Review | H58: 3486.24 | I58: 3486.24 | J58: Paid | K58: No | L58: None | M58: M. Diaz | N58: =H58-I58 -> 0 | O58: =IF(E58="","",E58-C58) -> 12 | P58: =IF(N58<=0,0,TODAY()-D58) -> 0 | Q58: =IF(N58<=0,"Paid",IF(P58<=0,"Current",IF(P58<=30,"1-30",IF(P58<=60,"31-60",IF(P58<=90,"61-90","90+"))))) -> Paid | R58: =TEXT(C58,"mmm") -> May | S58: =TEXT(C58,"yyyy-mm") -> 2025-05
A59: INV-1167 | B59: Canyon Creek Medical | C59: 45801 | D59: 45831 | E59: 45870 | F59: West | G59: Lab Services | H59: 1529.33 | I59: 942.61 | J59: Partial | K59: No | L59: None | M59: K. Brown | N59: =H59-I59 -> 586.72 | O59: =IF(E59="","",E59-C59) -> 69 | P59: =IF(N59<=0,0,TODAY()-D59) -> 266 | Q59: =IF(N59<=0,"Paid",IF(P59<=0,"Current",IF(P59<=30,"1-30",IF(P59<=60,"31-60",IF(P59<=90,"61-90","90+"))))) -> 90+ | R59: =TEXT(C59,"mmm") -> May | S59: =TEXT(C59,"yyyy-mm") -> 2025-05
A60: INV-1154 | B60: Metro Family Care | C60: 45807 | D60: 45837 | E60: 45851 | F60: West | G60: Claims Review | H60: 3539.51 | I60: 3539.51 | J60: Paid | K60: No | L60: None | M60: S. Patel | N60: =H60-I60 -> 0 | O60: =IF(E60="","",E60-C60) -> 44 | P60: =IF(N60<=0,0,TODAY()-D60) -> 0 | Q60: =IF(N60<=0,"Paid",IF(P60<=0,"Current",IF(P60<=30,"1-30",IF(P60<=60,"31-60",IF(P60<=90,"61-90","90+"))))) -> Paid | R60: =TEXT(C60,"mmm") -> May | S60: =TEXT(C60,"yyyy-mm") -> 2025-05
A61: INV-1047 | B61: Prime Family Clinic | C61: 45808 | D61: 45838 | E61: 45836 | F61: Central | G61: Billing Support | H61: 538.49 | I61: 538.49 | J61: Paid | K61: No | L61: None | M61: J. Smith | N61: =H61-I61 -> 0 | O61: =IF(E61="","",E61-C61) -> 28 | P61: =IF(N61<=0,0,TODAY()-D61) -> 0 | Q61: =IF(N61<=0,"Paid",IF(P61<=0,"Current",IF(P61<=30,"1-30",IF(P61<=60,"31-60",IF(P61<=90,"61-90","90+"))))) -> Paid | R61: =TEXT(C61,"mmm") -> May | S61: =TEXT(C61,"yyyy-mm") -> 2025-05
A62: INV-1249 | B62: Oak Health Group | C62: 45808 | D62: 45838 | F62: Central | G62: Claims Review | H62: 1009.39 | I62: 0 | J62: Unpaid | K62: No | L62: None | M62: S. Patel | N62: =H62-I62 -> 1009.39 | O62: =IF(E62="","",E62-C62) | P62: =IF(N62<=0,0,TODAY()-D62) -> 259 | Q62: =IF(N62<=0,"Paid",IF(P62<=0,"Current",IF(P62<=30,"1-30",IF(P62<=60,"31-60",IF(P62<=90,"61-90","90+"))))) -> 90+ | R62: =TEXT(C62,"mmm") -> May | S62: =TEXT(C62,"yyyy-mm") -> 2025-05
A63: INV-1187 | B63: Canyon Creek Medical | C63: 45809 | D63: 45839 | E63: 45845 | F63: Central | G63: Billing Support | H63: 525.72 | I63: 525.72 | J63: Paid | K63: No | L63: None | M63: M. Diaz | N63: =H63-I63 -> 0 | O63: =IF(E63="","",E63-C63) -> 36 | P63: =IF(N63<=0,0,TODAY()-D63) -> 0 | Q63: =IF(N63<=0,"Paid",IF(P63<=0,"Current",IF(P63<=30,"1-30",IF(P63<=60,"31-60",IF(P63<=90,"61-90","90+"))))) -> Paid | R63: =TEXT(C63,"mmm") -> Jun | S63: =TEXT(C63,"yyyy-mm") -> 2025-06
A64: INV-1178 | B64: Sunrise Medical Partners | C64: 45812 | D64: 45842 | E64: 45852 | F64: North | G64: RCM Consulting | H64: 1727.9 | I64: 1727.9 | J64: Paid | K64: No | L64: None | M64: M. Diaz | N64: =H64-I64 -> 0 | O64: =IF(E64="","",E64-C64) -> 40 | P64: =IF(N64<=0,0,TODAY()-D64) -> 0 | Q64: =IF(N64<=0,"Paid",IF(P64<=0,"Current",IF(P64<=30,"1-30",IF(P64<=60,"31-60",IF(P64<=90,"61-90","90+"))))) -> Paid | R64: =TEXT(C64,"mmm") -> Jun | S64: =TEXT(C64,"yyyy-mm") -> 2025-06
A65: INV-1101 | B65: Evergreen Pediatrics | C65: 45814 | D65: 45844 | F65: Central | G65: RCM Consulting | H65: 8058.74 | I65: 0 | J65: Unpaid | K65: Yes | L65: Missing info | M65: R. Nguyen | N65: =H65-I65 -> 8058.74 | O65: =IF(E65="","",E65-C65) | P65: =IF(N65<=0,0,TODAY()-D65) -> 253 | Q65: =IF(N65<=0,"Paid",IF(P65<=0,"Current",IF(P65<=30,"1-30",IF(P65<=60,"31-60",IF(P65<=90,"61-90","90+"))))) -> 90+ | R65: =TEXT(C65,"mmm") -> Jun | S65: =TEXT(C65,"yyyy-mm") -> 2025-06
A66: INV-1221 | B66: Oak Health Group | C66: 45814 | D66: 45844 | E66: 45854 | F66: North | G66: Claims Review | H66: 2175.12 | I66: 2175.12 | J66: Paid | K66: No | L66: None | M66: M. Diaz | N66: =H66-I66 -> 0 | O66: =IF(E66="","",E66-C66) -> 40 | P66: =IF(N66<=0,0,TODAY()-D66) -> 0 | Q66: =IF(N66<=0,"Paid",IF(P66<=0,"Current",IF(P66<=30,"1-30",IF(P66<=60,"31-60",IF(P66<=90,"61-90","90+"))))) -> Paid | R66: =TEXT(C66,"mmm") -> Jun | S66: =TEXT(C66,"yyyy-mm") -> 2025-06
A67: INV-1215 | B67: Trinity Wellness | C67: 45818 | D67: 45848 | E67: 45847 | F67: Central | G67: RCM Consulting | H67: 5100.61 | I67: 5100.61 | J67: Paid | K67: No | L67: None | M67: K. Brown | N67: =H67-I67 -> 0 | O67: =IF(E67="","",E67-C67) -> 29 | P67: =IF(N67<=0,0,TODAY()-D67) -> 0 | Q67: =IF(N67<=0,"Paid",IF(P67<=0,"Current",IF(P67<=30,"1-30",IF(P67<=60,"31-60",IF(P67<=90,"61-90","90+"))))) -> Paid | R67: =TEXT(C67,"mmm") -> Jun | S67: =TEXT(C67,"yyyy-mm") -> 2025-06
A68: INV-1183 | B68: Blue Ridge Medical | C68: 45819 | D68: 45849 | F68: North | G68: Billing Support | H68: 1433.84 | I68: 0 | J68: Unpaid | K68: Yes | L68: Eligibility issue | M68: M. Diaz | N68: =H68-I68 -> 1433.84 | O68: =IF(E68="","",E68-C68) | P68: =IF(N68<=0,0,TODAY()-D68) -> 248 | Q68: =IF(N68<=0,"Paid",IF(P68<=0,"Current",IF(P68<=30,"1-30",IF(P68<=60,"31-60",IF(P68<=90,"61-90","90+"))))) -> 90+ | R68: =TEXT(C68,"mmm") -> Jun | S68: =TEXT(C68,"yyyy-mm") -> 2025-06
A69: INV-1228 | B69: Horizon Medical | C69: 45820 | D69: 45850 | E69: 45865 | F69: Central | G69: Billing Support | H69: 1831.58 | I69: 1831.58 | J69: Paid | K69: No | L69: None | M69: S. Patel | N69: =H69-I69 -> 0 | O69: =IF(E69="","",E69-C69) -> 45 | P69: =IF(N69<=0,0,TODAY()-D69) -> 0 | Q69: =IF(N69<=0,"Paid",IF(P69<=0,"Current",IF(P69<=30,"1-30",IF(P69<=60,"31-60",IF(P69<=90,"61-90","90+"))))) -> Paid | R69: =TEXT(C69,"mmm") -> Jun | S69: =TEXT(C69,"yyyy-mm") -> 2025-06
A70: INV-1061 | B70: Blue Ridge Medical | C70: 45822 | D70: 45852 | E70: 45866 | F70: West | G70: Claims Review | H70: 4284.25 | I70: 4284.25 | J70: Paid | K70: No | L70: None | M70: S. Patel | N70: =H70-I70 -> 0 | O70: =IF(E70="","",E70-C70) -> 44 | P70: =IF(N70<=0,0,TODAY()-D70) -> 0 | Q70: =IF(N70<=0,"Paid",IF(P70<=0,"Current",IF(P70<=30,"1-30",IF(P70<=60,"31-60",IF(P70<=90,"61-90","90+"))))) -> Paid | R70: =TEXT(C70,"mmm") -> Jun | S70: =TEXT(C70,"yyyy-mm") -> 2025-06
A71: INV-1042 | B71: Lakeside Imaging | C71: 45824 | D71: 45854 | E71: 45871 | F71: South | G71: Revenue Audit | H71: 2574.5 | I71: 2574.5 | J71: Paid | K71: No | L71: None | M71: J. Smith | N71: =H71-I71 -> 0 | O71: =IF(E71="","",E71-C71) -> 47 | P71: =IF(N71<=0,0,TODAY()-D71) -> 0 | Q71: =IF(N71<=0,"Paid",IF(P71<=0,"Current",IF(P71<=30,"1-30",IF(P71<=60,"31-60",IF(P71<=90,"61-90","90+"))))) -> Paid | R71: =TEXT(C71,"mmm") -> Jun | S71: =TEXT(C71,"yyyy-mm") -> 2025-06
A72: INV-1020 | B72: Sunrise Medical Partners | C72: 45825 | D72: 45855 | E72: 45874 | F72: Central | G72: Revenue Audit | H72: 1766.1 | I72: 1766.1 | J72: Paid | K72: No | L72: None | M72: R. Nguyen | N72: =H72-I72 -> 0 | O72: =IF(E72="","",E72-C72) -> 49 | P72: =IF(N72<=0,0,TODAY()-D72) -> 0 | Q72: =IF(N72<=0,"Paid",IF(P72<=0,"Current",IF(P72<=30,"1-30",IF(P72<=60,"31-60",IF(P72<=90,"61-90","90+"))))) -> Paid | R72: =TEXT(C72,"mmm") -> Jun | S72: =TEXT(C72,"yyyy-mm") -> 2025-06
A73: INV-1030 | B73: Valley Care Center | C73: 45828 | D73: 45858 | F73: North | G73: RCM Consulting | H73: 5429.12 | I73: 2910.41 | J73: Partial | K73: Yes | L73: Late payment | M73: R. Nguyen | N73: =H73-I73 -> 2518.71 | O73: =IF(E73="","",E73-C73) | P73: =IF(N73<=0,0,TODAY()-D73) -> 239 | Q73: =IF(N73<=0,"Paid",IF(P73<=0,"Current",IF(P73<=30,"1-30",IF(P73<=60,"31-60",IF(P73<=90,"61-90","90+"))))) -> 90+ | R73: =TEXT(C73,"mmm") -> Jun | S73: =TEXT(C73,"yyyy-mm") -> 2025-06
A74: INV-1172 | B74: Metro Family Care | C74: 45830 | D74: 45860 | E74: 45862 | F74: West | G74: Billing Support | H74: 1212.77 | I74: 1212.77 | J74: Paid | K74: No | L74: None | M74: J. Smith | N74: =H74-I74 -> 0 | O74: =IF(E74="","",E74-C74) -> 32 | P74: =IF(N74<=0,0,TODAY()-D74) -> 0 | Q74: =IF(N74<=0,"Paid",IF(P74<=0,"Current",IF(P74<=30,"1-30",IF(P74<=60,"31-60",IF(P74<=90,"61-90","90+"))))) -> Paid | R74: =TEXT(C74,"mmm") -> Jun | S74: =TEXT(C74,"yyyy-mm") -> 2025-06
A75: INV-1241 | B75: Canyon Creek Medical | C75: 45830 | D75: 45860 | E75: 45902 | F75: South | G75: Imaging | H75: 1902.94 | I75: 950.53 | J75: Partial | K75: No | L75: None | M75: K. Brown | N75: =H75-I75 -> 952.41 | O75: =IF(E75="","",E75-C75) -> 72 | P75: =IF(N75<=0,0,TODAY()-D75) -> 237 | Q75: =IF(N75<=0,"Paid",IF(P75<=0,"Current",IF(P75<=30,"1-30",IF(P75<=60,"31-60",IF(P75<=90,"61-90","90+"))))) -> 90+ | R75: =TEXT(C75,"mmm") -> Jun | S75: =TEXT(C75,"yyyy-mm") -> 2025-06
A76: INV-1054 | B76: Valley Care Center | C76: 45832 | D76: 45862 | F76: South | G76: Imaging | H76: 1132.74 | I76: 0 | J76: Unpaid | K76: Yes | L76: Denied claim | M76: J. Smith | N76: =H76-I76 -> 1132.74 | O76: =IF(E76="","",E76-C76) | P76: =IF(N76<=0,0,TODAY()-D76) -> 235 | Q76: =IF(N76<=0,"Paid",IF(P76<=0,"Current",IF(P76<=30,"1-30",IF(P76<=60,"31-60",IF(P76<=90,"61-90","90+"))))) -> 90+ | R76: =TEXT(C76,"mmm") -> Jun | S76: =TEXT(C76,"yyyy-mm") -> 2025-06
A77: INV-1121 | B77: Trinity Wellness | C77: 45832 | D77: 45862 | E77: 45847 | F77: West | G77: RCM Consulting | H77: 1904.36 | I77: 1904.36 | J77: Paid | K77: No | L77: None | M77: M. Diaz | N77: =H77-I77 -> 0 | O77: =IF(E77="","",E77-C77) -> 15 | P77: =IF(N77<=0,0,TODAY()-D77) -> 0 | Q77: =IF(N77<=0,"Paid",IF(P77<=0,"Current",IF(P77<=30,"1-30",IF(P77<=60,"31-60",IF(P77<=90,"61-90","90+"))))) -> Paid | R77: =TEXT(C77,"mmm") -> Jun | S77: =TEXT(C77,"yyyy-mm") -> 2025-06
A78: INV-1141 | B78: Red Oak Wellness | C78: 45832 | D78: 45862 | E78: 45883 | F78: West | G78: RCM Consulting | H78: 5985.87 | I78: 1600.45 | J78: Partial | K78: Yes | L78: Missing info | M78: S. Patel | N78: =H78-I78 -> 4385.42 | O78: =IF(E78="","",E78-C78) -> 51 | P78: =IF(N78<=0,0,TODAY()-D78) -> 235 | Q78: =IF(N78<=0,"Paid",IF(P78<=0,"Current",IF(P78<=30,"1-30",IF(P78<=60,"31-60",IF(P78<=90,"61-90","90+"))))) -> 90+ | R78: =TEXT(C78,"mmm") -> Jun | S78: =TEXT(C78,"yyyy-mm") -> 2025-06
A79: INV-1165 | B79: Horizon Medical | C79: 45832 | D79: 45862 | F79: South | G79: Imaging | H79: 2929.7 | I79: 2200.42 | J79: Partial | K79: Yes | L79: Late payment | M79: J. Smith | N79: =H79-I79 -> 729.28 | O79: =IF(E79="","",E79-C79) | P79: =IF(N79<=0,0,TODAY()-D79) -> 235 | Q79: =IF(N79<=0,"Paid",IF(P79<=0,"Current",IF(P79<=30,"1-30",IF(P79<=60,"31-60",IF(P79<=90,"61-90","90+"))))) -> 90+ | R79: =TEXT(C79,"mmm") -> Jun | S79: =TEXT(C79,"yyyy-mm") -> 2025-06
A80: INV-1232 | B80: Red Oak Wellness | C80: 45835 | D80: 45865 | E80: 45869 | F80: Central | G80: Revenue Audit | H80: 5206.77 | I80: 5206.77 | J80: Paid | K80: No | L80: None | M80: R. Nguyen | N80: =H80-I80 -> 0 | O80: =IF(E80="","",E80-C80) -> 34 | P80: =IF(N80<=0,0,TODAY()-D80) -> 0 | Q80: =IF(N80<=0,"Paid",IF(P80<=0,"Current",IF(P80<=30,"1-30",IF(P80<=60,"31-60",IF(P80<=90,"61-90","90+"))))) -> Paid | R80: =TEXT(C80,"mmm") -> Jun | S80: =TEXT(C80,"yyyy-mm") -> 2025-06
A81: INV-1125 | B81: Oak Health Group | C81: 45837 | D81: 45867 | E81: 45868 | F81: Central | G81: Imaging | H81: 4066.24 | I81: 3324.49 | J81: Partial | K81: No | L81: None | M81: K. Brown | N81: =H81-I81 -> 741.75 | O81: =IF(E81="","",E81-C81) -> 31 | P81: =IF(N81<=0,0,TODAY()-D81) -> 230 | Q81: =IF(N81<=0,"Paid",IF(P81<=0,"Current",IF(P81<=30,"1-30",IF(P81<=60,"31-60",IF(P81<=90,"61-90","90+"))))) -> 90+ | R81: =TEXT(C81,"mmm") -> Jun | S81: =TEXT(C81,"yyyy-mm") -> 2025-06
A82: INV-1023 | B82: Hillcrest Diagnostics | C82: 45838 | D82: 45868 | E82: 45882 | F82: East | G82: Revenue Audit | H82: 1835.46 | I82: 1835.46 | J82: Paid | K82: No | L82: None | M82: K. Brown | N82: =H82-I82 -> 0 | O82: =IF(E82="","",E82-C82) -> 44 | P82: =IF(N82<=0,0,TODAY()-D82) -> 0 | Q82: =IF(N82<=0,"Paid",IF(P82<=0,"Current",IF(P82<=30,"1-30",IF(P82<=60,"31-60",IF(P82<=90,"61-90","90+"))))) -> Paid | R82: =TEXT(C82,"mmm") -> Jun | S82: =TEXT(C82,"yyyy-mm") -> 2025-06
A83: INV-1043 | B83: Trinity Wellness | C83: 45838 | D83: 45868 | F83: South | G83: Imaging | H83: 978.46 | I83: 715.59 | J83: Partial | K83: Yes | L83: Coding issue | M83: K. Brown | N83: =H83-I83 -> 262.87 | O83: =IF(E83="","",E83-C83) | P83: =IF(N83<=0,0,TODAY()-D83) -> 229 | Q83: =IF(N83<=0,"Paid",IF(P83<=0,"Current",IF(P83<=30,"1-30",IF(P83<=60,"31-60",IF(P83<=90,"61-90","90+"))))) -> 90+ | R83: =TEXT(C83,"mmm") -> Jun | S83: =TEXT(C83,"yyyy-mm") -> 2025-06
A84: INV-1018 | B84: Valley Care Center | C84: 45839 | D84: 45869 | E84: 45851 | F84: North | G84: Imaging | H84: 7618.04 | I84: 7618.04 | J84: Paid | K84: No | L84: None | M84: S. Patel | N84: =H84-I84 -> 0 | O84: =IF(E84="","",E84-C84) -> 12 | P84: =IF(N84<=0,0,TODAY()-D84) -> 0 | Q84: =IF(N84<=0,"Paid",IF(P84<=0,"Current",IF(P84<=30,"1-30",IF(P84<=60,"31-60",IF(P84<=90,"61-90","90+"))))) -> Paid | R84: =TEXT(C84,"mmm") -> Jul | S84: =TEXT(C84,"yyyy-mm") -> 2025-07
A85: INV-1252 | B85: NorthStar Clinic | C85: 45840 | D85: 45870 | E85: 45851 | F85: South | G85: Lab Services | H85: 2241.23 | I85: 2241.23 | J85: Paid | K85: No | L85: None | M85: J. Smith | N85: =H85-I85 -> 0 | O85: =IF(E85="","",E85-C85) -> 11 | P85: =IF(N85<=0,0,TODAY()-D85) -> 0 | Q85: =IF(N85<=0,"Paid",IF(P85<=0,"Current",IF(P85<=30,"1-30",IF(P85<=60,"31-60",IF(P85<=90,"61-90","90+"))))) -> Paid | R85: =TEXT(C85,"mmm") -> Jul | S85: =TEXT(C85,"yyyy-mm") -> 2025-07
A86: INV-1229 | B86: Summit Health | C86: 45841 | D86: 45871 | E86: 45870 | F86: North | G86: Revenue Audit | H86: 1896.06 | I86: 1896.06 | J86: Paid | K86: No | L86: None | M86: S. Patel | N86: =H86-I86 -> 0 | O86: =IF(E86="","",E86-C86) -> 29 | P86: =IF(N86<=0,0,TODAY()-D86) -> 0 | Q86: =IF(N86<=0,"Paid",IF(P86<=0,"Current",IF(P86<=30,"1-30",IF(P86<=60,"31-60",IF(P86<=90,"61-90","90+"))))) -> Paid | R86: =TEXT(C86,"mmm") -> Jul | S86: =TEXT(C86,"yyyy-mm") -> 2025-07
A87: INV-1026 | B87: Oak Health Group | C87: 45844 | D87: 45874 | E87: 45867 | F87: South | G87: Imaging | H87: 4030.02 | I87: 4030.02 | J87: Paid | K87: No | L87: None | M87: S. Patel | N87: =H87-I87 -> 0 | O87: =IF(E87="","",E87-C87) -> 23 | P87: =IF(N87<=0,0,TODAY()-D87) -> 0 | Q87: =IF(N87<=0,"Paid",IF(P87<=0,"Current",IF(P87<=30,"1-30",IF(P87<=60,"31-60",IF(P87<=90,"61-90","90+"))))) -> Paid | R87: =TEXT(C87,"mmm") -> Jul | S87: =TEXT(C87,"yyyy-mm") -> 2025-07
A88: INV-1014 | B88: Hillcrest Diagnostics | C88: 45845 | D88: 45875 | E88: 45894 | F88: Central | G88: Lab Services | H88: 2634.24 | I88: 1873.36 | J88: Partial | K88: Yes | L88: Missing info | M88: R. Nguyen | N88: =H88-I88 -> 760.88 | O88: =IF(E88="","",E88-C88) -> 49 | P88: =IF(N88<=0,0,TODAY()-D88) -> 222 | Q88: =IF(N88<=0,"Paid",IF(P88<=0,"Current",IF(P88<=30,"1-30",IF(P88<=60,"31-60",IF(P88<=90,"61-90","90+"))))) -> 90+ | R88: =TEXT(C88,"mmm") -> Jul | S88: =TEXT(C88,"yyyy-mm") -> 2025-07
A89: INV-1077 | B89: Lakeside Imaging | C89: 45849 | D89: 45879 | E89: 45862 | F89: East | G89: Billing Support | H89: 1842.6 | I89: 1842.6 | J89: Paid | K89: Yes | L89: Duplicate invoice | M89: S. Patel | N89: =H89-I89 -> 0 | O89: =IF(E89="","",E89-C89) -> 13 | P89: =IF(N89<=0,0,TODAY()-D89) -> 0 | Q89: =IF(N89<=0,"Paid",IF(P89<=0,"Current",IF(P89<=30,"1-30",IF(P89<=60,"31-60",IF(P89<=90,"61-90","90+"))))) -> Paid | R89: =TEXT(C89,"mmm") -> Jul | S89: =TEXT(C89,"yyyy-mm") -> 2025-07
A90: INV-1012 | B90: Westgate Family Health | C90: 45851 | D90: 45881 | E90: 45891 | F90: Central | G90: Claims Review | H90: 2097.6 | I90: 2097.6 | J90: Paid | K90: No | L90: None | M90: S. Patel | N90: =H90-I90 -> 0 | O90: =IF(E90="","",E90-C90) -> 40 | P90: =IF(N90<=0,0,TODAY()-D90) -> 0 | Q90: =IF(N90<=0,"Paid",IF(P90<=0,"Current",IF(P90<=30,"1-30",IF(P90<=60,"31-60",IF(P90<=90,"61-90","90+"))))) -> Paid | R90: =TEXT(C90,"mmm") -> Jul | S90: =TEXT(C90,"yyyy-mm") -> 2025-07
A91: INV-1029 | B91: Evergreen Pediatrics | C91: 45852 | D91: 45882 | E91: 45888 | F91: West | G91: Billing Support | H91: 1832.5 | I91: 1185.85 | J91: Partial | K91: No | L91: None | M91: K. Brown | N91: =H91-I91 -> 646.65 | O91: =IF(E91="","",E91-C91) -> 36 | P91: =IF(N91<=0,0,TODAY()-D91) -> 215 | Q91: =IF(N91<=0,"Paid",IF(P91<=0,"Current",IF(P91<=30,"1-30",IF(P91<=60,"31-60",IF(P91<=90,"61-90","90+"))))) -> 90+ | R91: =TEXT(C91,"mmm") -> Jul | S91: =TEXT(C91,"yyyy-mm") -> 2025-07
A92: INV-1212 | B92: Trinity Wellness | C92: 45852 | D92: 45882 | E92: 45883 | F92: East | G92: Claims Review | H92: 680.97 | I92: 680.97 | J92: Paid | K92: No | L92: None | M92: M. Diaz | N92: =H92-I92 -> 0 | O92: =IF(E92="","",E92-C92) -> 31 | P92: =IF(N92<=0,0,TODAY()-D92) -> 0 | Q92: =IF(N92<=0,"Paid",IF(P92<=0,"Current",IF(P92<=30,"1-30",IF(P92<=60,"31-60",IF(P92<=90,"61-90","90+"))))) -> Paid | R92: =TEXT(C92,"mmm") -> Jul | S92: =TEXT(C92,"yyyy-mm") -> 2025-07
A93: INV-1044 | B93: Summit Health | C93: 45853 | D93: 45883 | E93: 45873 | F93: South | G93: Revenue Audit | H93: 2727.47 | I93: 2727.47 | J93: Paid | K93: No | L93: None | M93: J. Smith | N93: =H93-I93 -> 0 | O93: =IF(E93="","",E93-C93) -> 20 | P93: =IF(N93<=0,0,TODAY()-D93) -> 0 | Q93: =IF(N93<=0,"Paid",IF(P93<=0,"Current",IF(P93<=30,"1-30",IF(P93<=60,"31-60",IF(P93<=90,"61-90","90+"))))) -> Paid | R93: =TEXT(C93,"mmm") -> Jul | S93: =TEXT(C93,"yyyy-mm") -> 2025-07
A94: INV-1092 | B94: Evergreen Pediatrics | C94: 45856 | D94: 45886 | E94: 45911 | F94: Central | G94: RCM Consulting | H94: 4614.52 | I94: 4614.52 | J94: Paid | K94: No | L94: None | M94: K. Brown | N94: =H94-I94 -> 0 | O94: =IF(E94="","",E94-C94) -> 55 | P94: =IF(N94<=0,0,TODAY()-D94) -> 0 | Q94: =IF(N94<=0,"Paid",IF(P94<=0,"Current",IF(P94<=30,"1-30",IF(P94<=60,"31-60",IF(P94<=90,"61-90","90+"))))) -> Paid | R94: =TEXT(C94,"mmm") -> Jul | S94: =TEXT(C94,"yyyy-mm") -> 2025-07
A95: INV-1116 | B95: Evergreen Pediatrics | C95: 45857 | D95: 45887 | F95: North | G95: RCM Consulting | H95: 7270.83 | I95: 0 | J95: Unpaid | K95: No | L95: None | M95: R. Nguyen | N95: =H95-I95 -> 7270.83 | O95: =IF(E95="","",E95-C95) | P95: =IF(N95<=0,0,TODAY()-D95) -> 210 | Q95: =IF(N95<=0,"Paid",IF(P95<=0,"Current",IF(P95<=30,"1-30",IF(P95<=60,"31-60",IF(P95<=90,"61-90","90+"))))) -> 90+ | R95: =TEXT(C95,"mmm") -> Jul | S95: =TEXT(C95,"yyyy-mm") -> 2025-07
A96: INV-1255 | B96: Valley Care Center | C96: 45857 | D96: 45887 | F96: North | G96: RCM Consulting | H96: 8061.77 | I96: 0 | J96: Unpaid | K96: Yes | L96: Missing info | M96: S. Patel | N96: =H96-I96 -> 8061.77 | O96: =IF(E96="","",E96-C96) | P96: =IF(N96<=0,0,TODAY()-D96) -> 210 | Q96: =IF(N96<=0,"Paid",IF(P96<=0,"Current",IF(P96<=30,"1-30",IF(P96<=60,"31-60",IF(P96<=90,"61-90","90+"))))) -> 90+ | R96: =TEXT(C96,"mmm") -> Jul | S96: =TEXT(C96,"yyyy-mm") -> 2025-07
A97: INV-1076 | B97: Metro Family Care | C97: 45859 | D97: 45889 | E97: 45898 | F97: West | G97: Imaging | H97: 4902.92 | I97: 3729.02 | J97: Partial | K97: Yes | L97: Coding issue | M97: K. Brown | N97: =H97-I97 -> 1173.9 | O97: =IF(E97="","",E97-C97) -> 39 | P97: =IF(N97<=0,0,TODAY()-D97) -> 208 | Q97: =IF(N97<=0,"Paid",IF(P97<=0,"Current",IF(P97<=30,"1-30",IF(P97<=60,"31-60",IF(P97<=90,"61-90","90+"))))) -> 90+ | R97: =TEXT(C97,"mmm") -> Jul | S97: =TEXT(C97,"yyyy-mm") -> 2025-07
A98: INV-1082 | B98: Canyon Creek Medical | C98: 45861 | D98: 45891 | E98: 45886 | F98: North | G98: Imaging | H98: 2437.88 | I98: 2437.88 | J98: Paid | K98: Yes | L98: Duplicate invoice | M98: M. Diaz | N98: =H98-I98 -> 0 | O98: =IF(E98="","",E98-C98) -> 25 | P98: =IF(N98<=0,0,TODAY()-D98) -> 0 | Q98: =IF(N98<=0,"Paid",IF(P98<=0,"Current",IF(P98<=30,"1-30",IF(P98<=60,"31-60",IF(P98<=90,"61-90","90+"))))) -> Paid | R98: =TEXT(C98,"mmm") -> Jul | S98: =TEXT(C98,"yyyy-mm") -> 2025-07
A99: INV-1211 | B99: Blue Ridge Medical | C99: 45861 | D99: 45891 | E99: 45896 | F99: West | G99: RCM Consulting | H99: 6445.66 | I99: 6445.66 | J99: Paid | K99: Yes | L99: Coding issue | M99: R. Nguyen | N99: =H99-I99 -> 0 | O99: =IF(E99="","",E99-C99) -> 35 | P99: =IF(N99<=0,0,TODAY()-D99) -> 0 | Q99: =IF(N99<=0,"Paid",IF(P99<=0,"Current",IF(P99<=30,"1-30",IF(P99<=60,"31-60",IF(P99<=90,"61-90","90+"))))) -> Paid | R99: =TEXT(C99,"mmm") -> Jul | S99: =TEXT(C99,"yyyy-mm") -> 2025-07
A100: INV-1059 | B100: Metro Family Care | C100: 45863 | D100: 45893 | E100: 45885 | F100: South | G100: Billing Support | H100: 1003.36 | I100: 1003.36 | J100: Paid | K100: No | L100: None | M100: M. Diaz | N100: =H100-I100 -> 0 | O100: =IF(E100="","",E100-C100) -> 22 | P100: =IF(N100<=0,0,TODAY()-D100) -> 0 | Q100: =IF(N100<=0,"Paid",IF(P100<=0,"Current",IF(P100<=30,"1-30",IF(P100<=60,"31-60",IF(P100<=90,"61-90","90+"))))) -> Paid | R100: =TEXT(C100,"mmm") -> Jul | S100: =TEXT(C100,"yyyy-mm") -> 2025-07
A101: INV-1117 | B101: Parkview Internal Medicine | C101: 45863 | D101: 45893 | E101: 45917 | F101: South | G101: RCM Consulting | H101: 2908.24 | I101: 2908.24 | J101: Paid | K101: No | L101: None | M101: M. Diaz | N101: =H101-I101 -> 0 | O101: =IF(E101="","",E101-C101) -> 54 | P101: =IF(N101<=0,0,TODAY()-D101) -> 0 | Q101: =IF(N101<=0,"Paid",IF(P101<=0,"Current",IF(P101<=30,"1-30",IF(P101<=60,"31-60",IF(P101<=90,"61-90","90+"))))) -> Paid | R101: =TEXT(C101,"mmm") -> Jul | S101: =TEXT(C101,"yyyy-mm") -> 2025-07
A102: INV-1213 | B102: Westgate Family Health | C102: 45864 | D102: 45894 | E102: 45911 | F102: North | G102: Claims Review | H102: 2301.42 | I102: 2301.42 | J102: Paid | K102: No | L102: None | M102: S. Patel | N102: =H102-I102 -> 0 | O102: =IF(E102="","",E102-C102) -> 47 | P102: =IF(N102<=0,0,TODAY()-D102) -> 0 | Q102: =IF(N102<=0,"Paid",IF(P102<=0,"Current",IF(P102<=30,"1-30",IF(P102<=60,"31-60",IF(P102<=90,"61-90","90+"))))) -> Paid | R102: =TEXT(C102,"mmm") -> Jul | S102: =TEXT(C102,"yyyy-mm") -> 2025-07
A103: INV-1226 | B103: Prime Family Clinic | C103: 45864 | D103: 45894 | F103: North | G103: RCM Consulting | H103: 5436.89 | I103: 0 | J103: Unpaid | K103: Yes | L103: Eligibility issue | M103: R. Nguyen | N103: =H103-I103 -> 5436.89 | O103: =IF(E103="","",E103-C103) | P103: =IF(N103<=0,0,TODAY()-D103) -> 203 | Q103: =IF(N103<=0,"Paid",IF(P103<=0,"Current",IF(P103<=30,"1-30",IF(P103<=60,"31-60",IF(P103<=90,"61-90","90+"))))) -> 90+ | R103: =TEXT(C103,"mmm") -> Jul | S103: =TEXT(C103,"yyyy-mm") -> 2025-07
A104: INV-1227 | B104: Trinity Wellness | C104: 45865 | D104: 45895 | F104: North | G104: Billing Support | H104: 473.86 | I104: 0 | J104: Unpaid | K104: Yes | L104: Missing info | M104: R. Nguyen | N104: =H104-I104 -> 473.86 | O104: =IF(E104="","",E104-C104) | P104: =IF(N104<=0,0,TODAY()-D104) -> 202 | Q104: =IF(N104<=0,"Paid",IF(P104<=0,"Current",IF(P104<=30,"1-30",IF(P104<=60,"31-60",IF(P104<=90,"61-90","90+"))))) -> 90+ | R104: =TEXT(C104,"mmm") -> Jul | S104: =TEXT(C104,"yyyy-mm") -> 2025-07
A105: INV-1236 | B105: Cedar Grove Health | C105: 45868 | D105: 45898 | F105: Central | G105: Revenue Audit | H105: 1630.12 | I105: 0 | J105: Unpaid | K105: No | L105: None | M105: A. Lopez | N105: =H105-I105 -> 1630.12 | O105: =IF(E105="","",E105-C105) | P105: =IF(N105<=0,0,TODAY()-D105) -> 199 | Q105: =IF(N105<=0,"Paid",IF(P105<=0,"Current",IF(P105<=30,"1-30",IF(P105<=60,"31-60",IF(P105<=90,"61-90","90+"))))) -> 90+ | R105: =TEXT(C105,"mmm") -> Jul | S105: =TEXT(C105,"yyyy-mm") -> 2025-07
A106: INV-1205 | B106: Evergreen Pediatrics | C106: 45869 | D106: 45899 | E106: 45890 | F106: West | G106: Lab Services | H106: 585.73 | I106: 585.73 | J106: Paid | K106: No | L106: None | M106: R. Nguyen | N106: =H106-I106 -> 0 | O106: =IF(E106="","",E106-C106) -> 21 | P106: =IF(N106<=0,0,TODAY()-D106) -> 0 | Q106: =IF(N106<=0,"Paid",IF(P106<=0,"Current",IF(P106<=30,"1-30",IF(P106<=60,"31-60",IF(P106<=90,"61-90","90+"))))) -> Paid | R106: =TEXT(C106,"mmm") -> Jul | S106: =TEXT(C106,"yyyy-mm") -> 2025-07
A107: INV-1250 | B107: NorthStar Clinic | C107: 45869 | D107: 45899 | E107: 45892 | F107: West | G107: Revenue Audit | H107: 3585.56 | I107: 3585.56 | J107: Paid | K107: No | L107: None | M107: R. Nguyen | N107: =H107-I107 -> 0 | O107: =IF(E107="","",E107-C107) -> 23 | P107: =IF(N107<=0,0,TODAY()-D107) -> 0 | Q107: =IF(N107<=0,"Paid",IF(P107<=0,"Current",IF(P107<=30,"1-30",IF(P107<=60,"31-60",IF(P107<=90,"61-90","90+"))))) -> Paid | R107: =TEXT(C107,"mmm") -> Jul | S107: =TEXT(C107,"yyyy-mm") -> 2025-07
...

Sheet Pivot_Tables
A1: Row Labels | B1: Sum of Billed_Amount | C1: Sum of Paid_Amount | E1: Row Labels | F1: Count of Invoice_ID
A2: 2025-03 | B2: 2659.04 | C2: 888.34 | E2: Coding issue | F2: 1 | H2: Average of Days_to_Pay
A3: 2025-04 | B3: 6589.59 | C3: 2632.67 | E3: Late payment | F3: 2 | H3: 35.76699
A4: 2025-05 | B4: 5036.44 | C4: 2839.11 | E4: Missing info | F4: 2
A5: 2025-06 | B5: 5985.87 | C5: 1600.45 | E5: Underpayment | F5: 1
A6: 2025-07 | B6: 6735.42 | C6: 4914.87 | E6: Grand Total | F6: 6
A7: 2025-09 | B7: 10968.76 | C7: 4407.27
A8: 2025-10 | B8: 1515.35 | C8: 433.89 | H8: Row Labels | I8: Count of Invoice_ID
A9: 2025-12 | B9: 2022.39 | C9: 1380.97 | H9: No | I9: 176
A10: Grand Total | B10: 41512.86 | C10: 19097.57 | H10: Yes | I10: 84
E11: Row Labels | F11: Sum of Outstanding_Balance | H11: Grand Total | I11: 260
E12: 31-60 | F12: 641.42
E13: 90+ | F13: 21773.87
E14: Grand Total | F14: 22415.29
A16: Row Labels | B16: Sum of Billed_Amount | C16: Sum of Paid_Amount
A17: Billing Support | B17: 6234.32 | C17: 3811.01
A18: Claims Review | B18: 8168.73 | C18: 3933.48
A19: Imaging | B19: 13007.86 | C19: 6795.58
A20: Lab Services | B20: 1529.33 | C20: 942.61 | E20: Row Labels | F20: Count of Invoice_ID
A21: RCM Consulting | B21: 12572.62 | C21: 3614.89 | E21: Paid | F21: 162
A22: Grand Total | B22: 41512.86 | C22: 19097.57 | E22: Partial | F22: 53
E23: Unpaid | F23: 45
E24: Grand Total | F24: 260
A25: Row Labels | B25: Sum of Billed_Amount | C25: Sum of Paid_Amount
A26: West | B26: 41512.86 | C26: 19097.57
A27: Grand Total | B27: 41512.86 | C27: 19097.57
E29: Days_Past_Due | F29: (Multiple Items)
E31: Sum of Outstanding_Balance
E32: 169889.43
E35: Count of Invoice_ID
E36: 260
A37: Row Labels | B37: Sum of Billed_Amount | C37: Sum of Paid_Amount
A38: 2025-03 | B38: 2659.04 | C38: 888.34
A39: 2025-04 | B39: 6589.59 | C39: 2632.67
A40: 2025-05 | B40: 5036.44 | C40: 2839.11
A41: 2025-06 | B41: 5985.87 | C41: 1600.45
A42: 2025-07 | B42: 6735.42 | C42: 4914.87
A43: 2025-09 | B43: 10968.76 | C43: 4407.27
A44: 2025-10 | B44: 1515.35 | C44: 433.89
A45: 2025-12 | B45: 2022.39 | C45: 1380.97
A46: Grand Total | B46: 41512.86 | C46: 19097.57

Sheet Revenue_Dashboard_v2.xlsx
A1: Total Billed | B1: Total Paid | C1: Outstanding | D1: Collection Rate | E1: Avg Days to Pay | F1: Unpaid Invoices | G1: $ Past Due 30+ | H1: Exception Rate
A2: =GETPIVOTDATA("Sum of Billed_Amount",Pivot_Tables!$A$1) -> 41512.86 | B2: =GETPIVOTDATA("Sum of Paid_Amount",Pivot_Tables!$A$1) -> 19097.57 | C2: =GETPIVOTDATA("Outstanding_Balance",Pivot_Tables!$E$11) -> 22415.29 | D2: =IFERROR(B2/A2,0) -> 0.46003985 | E2: =GETPIVOTDATA("Days_to_Pay",Pivot_Tables!$H$2) -> 35.76699 | F2: =GETPIVOTDATA("Invoice_ID",Pivot_Tables!$E$20,"Payment_Status","Unpaid") -> 45 | G2: =GETPIVOTDATA("Outstanding_Balance",Pivot_Tables!$E$31) -> 169889.43 | H2: =IFERROR(H3/H4,0) -> 0.32307692
H3: =GETPIVOTDATA("Invoice_ID",Pivot_Tables!$H$8,"Denial_or_Exception","Yes") -> 84
H4: =GETPIVOTDATA("Invoice_ID",Pivot_Tables!$E$35) -> 260
